{"version": "2.0", "notation_type": "Text", "composer": "\u59dc\u5914", "mode_properties": {"gong_lvlv": "None", "final_note": "None"}, "images": ["../../images/zhu_edition_101.png"], "content": [{"box_type": "Preface", "is_excluded_from_dataset": false, "is_line_break": false, "text_coordinates": [[373, 204], [425, 248]], "text_content": "\u6dbc"}, {"box_type": "Preface", "is_excluded_from_dataset": false, "is_line_break": false, "text_coordinates": [[370, 254], [429, 296]], "text_content": "\u89c0"}, {"box_type": "Preface", "is_excluded_from_dataset": false, "is_line_break": false, "text_coordinates": [[374, 301], [426, 343]], "text_content": "\u5728"}, {"box_type": "Preface", "is_excluded_from_dataset": false, "is_line_break": false, "text_coordinates": [[372, 347], [429, 389]], "text_content": "\u5b64"}, {"box_type": "Preface", "is_excluded_from_dataset": false, "is_line_break": false, "text_coordinates": [[378, 395], [423, 434]], "text_content": "\u5c71"}, {"box_type": "Preface", "is_excluded_from_dataset": false, "is_line_break": false, "text_coordinates": [[371, 442], [429, 480]], "text_content": "\u4e4b"}, {"box_type": "Preface", "is_excluded_from_dataset": false, "is_line_break": false, "text_coordinates": [[371, 488], [429, 532]], "text_content": "\u9e93"}, {"box_type": "Preface", "is_excluded_from_dataset": false, "is_line_break": false, "text_coordinates": [[374, 536], [429, 575]], "text_content": "\u5357"}, {"box_type": "Preface", "is_excluded_from_dataset": false, "is_line_break": false, "text_coordinates": [[372, 581], [427, 622]], "text_content": "\u5317"}, {"box_type": "Preface", "is_excluded_from_dataset": false, "is_line_break": false, "text_coordinates": [[374, 628], [429, 671]], "text_content": "\u6885"}, {"box_type": "Preface", "is_excluded_from_dataset": false, "is_line_break": false, "text_coordinates": [[374, 676], [429, 719]], "text_content": "\u6700"}, {"box_type": "Preface", "is_excluded_from_dataset": false, "is_line_break": false, "text_coordinates": [[374, 723], [429, 764]], "text_content": "\u5947"}, {"box_type": "Preface", "is_excluded_from_dataset": false, "is_line_break": false, "text_coordinates": [[372, 770], [429, 810]], "text_content": "\u7af9"}, {"box_type": "Preface", "is_excluded_from_dataset": false, "is_line_break": false, "text_coordinates": [[378, 818], [426, 860]], "text_content": "\u95a3"}, {"box_type": "Preface", "is_excluded_from_dataset": false, "is_line_break": false, "text_coordinates": [[371, 864], [429, 905]], "text_content": "\u5728"}, {"box_type": "Preface", "is_excluded_from_dataset": false, "is_line_break": false, "text_coordinates": [[375, 910], [428, 952]], "text_content": "\u6dbc"}, {"box_type": "Preface", "is_excluded_from_dataset": false, "is_line_break": true, "text_coordinates": [[373, 955], [431, 1001]], "text_content": "\u89c0"}, {"box_type": "Preface", "is_excluded_from_dataset": false, "is_line_break": false, "text_coordinates": [[309, 204], [361, 245]], "text_content": "\u897f"}, {"box_type": "Preface", "is_excluded_from_dataset": false, "is_line_break": false, "text_coordinates": [[306, 255], [361, 295]], "text_content": "\u4eca"}, {"box_type": "Preface", "is_excluded_from_dataset": false, "is_line_break": false, "text_coordinates": [[306, 299], [363, 347]], "text_content": "\u5ee2"}, {"box_type": "Music", "is_excluded_from_dataset": false, "is_line_break": false, "text_coordinates": [[569, 14], [625, 61]], "text_content": "\u861a", "notation_coordinates": null, "notation_content": null}, {"box_type": "Music", "is_excluded_from_dataset": false, "is_line_break": false, "text_coordinates": [[569, 64], [623, 109]], "text_content": "\u69a6", "notation_coordinates": null, "notation_content": null}, {"box_type": "Music", "is_excluded_from_dataset": false, "is_line_break": false, "text_coordinates": [[568, 115], [622, 152]], "text_content": "\u77f3", "notation_coordinates": null, "notation_content": null}, {"box_type": "Music", "is_excluded_from_dataset": false, "is_line_break": false, "text_coordinates": [[568, 161], [627, 201]], "text_content": "\u659c", "notation_coordinates": null, "notation_content": null}, {"box_type": "Music", "is_excluded_from_dataset": false, "is_line_break": false, "text_coordinates": [[569, 209], [624, 252]], "text_content": "\u59a8", "notation_coordinates": null, "notation_content": null}, {"box_type": "Music", "is_excluded_from_dataset": false, "is_line_break": false, "text_coordinates": [[569, 255], [624, 292]], "text_content": "\u7389", "notation_coordinates": null, "notation_content": null}, {"box_type": "Music", "is_excluded_from_dataset": false, "is_line_break": false, "text_coordinates": [[570, 298], [626, 340]], "text_content": "\u854a", "notation_coordinates": null, "notation_content": null}, {"box_type": "Music", "is_excluded_from_dataset": false, "is_line_break": false, "text_coordinates": [[567, 346], [624, 387]], "text_content": "\u677e", "notation_coordinates": null, "notation_content": null}, {"box_type": "Music", "is_excluded_from_dataset": false, "is_line_break": false, "text_coordinates": [[568, 394], [625, 432]], "text_content": "\u4f4e", "notation_coordinates": null, "notation_content": null}, {"box_type": "Music", "is_excluded_from_dataset": false, "is_line_break": false, "text_coordinates": [[569, 438], [623, 487]], "text_content": "\u8986", "notation_coordinates": null, "notation_content": null}, {"box_type": "Music", "is_excluded_from_dataset": false, "is_line_break": false, "text_coordinates": [[579, 489], [616, 524]], "text_content": "\u65e5", "notation_coordinates": null, "notation_content": null}, {"box_type": "Music", "is_excluded_from_dataset": false, "is_line_break": false, "text_coordinates": [[569, 532], [625, 580]], "text_content": "\u66ae", "notation_coordinates": null, "notation_content": null}, {"box_type": "Music", "is_excluded_from_dataset": false, "is_line_break": false, "text_coordinates": [[572, 582], [624, 626]], "text_content": "\u51a5", "notation_coordinates": null, "notation_content": null}, {"box_type": "Music", "is_excluded_from_dataset": false, "is_line_break": false, "text_coordinates": [[568, 629], [624, 673]], "text_content": "\u51a5", "notation_coordinates": null, "notation_content": null}, {"box_type": "Music", "is_excluded_from_dataset": false, "is_line_break": false, "text_coordinates": [[571, 688], [623, 695]], "text_content": "\u4e00", "notation_coordinates": null, "notation_content": null}, {"box_type": "Music", "is_excluded_from_dataset": false, "is_line_break": false, "text_coordinates": [[570, 721], [627, 765]], "text_content": "\u898b", "notation_coordinates": null, "notation_content": null}, {"box_type": "Music", "is_excluded_from_dataset": false, "is_line_break": false, "text_coordinates": [[570, 768], [627, 811]], "text_content": "\u4f86", "notation_coordinates": null, "notation_content": null}, {"box_type": "Music", "is_excluded_from_dataset": false, "is_line_break": false, "text_coordinates": [[571, 818], [627, 856]], "text_content": "\u7565", "notation_coordinates": null, "notation_content": null}, {"box_type": "Music", "is_excluded_from_dataset": false, "is_line_break": false, "text_coordinates": [[571, 864], [626, 901]], "text_content": "\u6bd4", "notation_coordinates": null, "notation_content": null}, {"box_type": "Music", "is_excluded_from_dataset": false, "is_line_break": false, "text_coordinates": [[572, 909], [629, 955]], "text_content": "\u5e74", "notation_coordinates": null, "notation_content": null}, {"box_type": "Music", "is_excluded_from_dataset": false, "is_line_break": true, "text_coordinates": [[575, 956], [630, 999]], "text_content": "\u6642", "notation_coordinates": null, "notation_content": null}, {"box_type": "Music", "is_excluded_from_dataset": false, "is_line_break": false, "text_coordinates": [[501, 15], [556, 63]], "text_content": "\u7626", "notation_coordinates": null, "notation_content": null}, {"box_type": "Music", "is_excluded_from_dataset": false, "is_line_break": false, "text_coordinates": [[508, 70], [553, 106]], "text_content": " ", "notation_coordinates": null, "notation_content": null}, {"box_type": "Music", "is_excluded_from_dataset": false, "is_line_break": false, "text_coordinates": [[507, 113], [558, 154]], "text_content": "\u6dbc", "notation_coordinates": null, "notation_content": null}, {"box_type": "Music", "is_excluded_from_dataset": false, "is_line_break": false, "text_coordinates": [[501, 158], [561, 204]], "text_content": "\u89c0", "notation_coordinates": null, "notation_content": null}, {"box_type": "Music", "is_excluded_from_dataset": false, "is_line_break": false, "text_coordinates": [[504, 208], [557, 247]], "text_content": "\u9152", "notation_coordinates": null, "notation_content": null}, {"box_type": "Music", "is_excluded_from_dataset": false, "is_line_break": false, "text_coordinates": [[501, 257], [555, 297]], "text_content": "\u521d", "notation_coordinates": null, "notation_content": null}, {"box_type": "Music", "is_excluded_from_dataset": false, "is_line_break": false, "text_coordinates": [[504, 302], [560, 340]], "text_content": "\u9192", "notation_coordinates": null, "notation_content": null}, {"box_type": "Music", "is_excluded_from_dataset": false, "is_line_break": false, "text_coordinates": [[503, 347], [560, 386]], "text_content": "\u7af9", "notation_coordinates": null, "notation_content": null}, {"box_type": "Music", "is_excluded_from_dataset": false, "is_line_break": false, "text_coordinates": [[507, 392], [555, 435]], "text_content": "\u95a3", "notation_coordinates": null, "notation_content": null}, {"box_type": "Music", "is_excluded_from_dataset": false, "is_line_break": false, "text_coordinates": [[506, 441], [558, 481]], "text_content": "\u541f", "notation_coordinates": null, "notation_content": null}, {"box_type": "Music", "is_excluded_from_dataset": false, "is_line_break": false, "text_coordinates": [[501, 487], [561, 531]], "text_content": "\u7e94", "notation_coordinates": null, "notation_content": null}, {"box_type": "Music", "is_excluded_from_dataset": false, "is_line_break": false, "text_coordinates": [[503, 533], [560, 578]], "text_content": "\u5c31", "notation_coordinates": null, "notation_content": null}, {"box_type": "Music", "is_excluded_from_dataset": false, "is_line_break": false, "text_coordinates": [[501, 581], [560, 623]], "text_content": "\u7336", "notation_coordinates": null, "notation_content": null}, {"box_type": "Music", "is_excluded_from_dataset": false, "is_line_break": false, "text_coordinates": [[505, 629], [559, 670]], "text_content": "\u6068", "notation_coordinates": null, "notation_content": null}, {"box_type": "Music", "is_excluded_from_dataset": false, "is_line_break": false, "text_coordinates": [[509, 676], [558, 713]], "text_content": "\u5e7d", "notation_coordinates": null, "notation_content": null}, {"box_type": "Music", "is_excluded_from_dataset": false, "is_line_break": false, "text_coordinates": [[504, 721], [559, 765]], "text_content": "\u9999", "notation_coordinates": null, "notation_content": null}, {"box_type": "Music", "is_excluded_from_dataset": false, "is_line_break": false, "text_coordinates": [[504, 769], [560, 809]], "text_content": "\u4f5c", "notation_coordinates": null, "notation_content": null}, {"box_type": "Music", "is_excluded_from_dataset": false, "is_line_break": false, "text_coordinates": [[504, 815], [561, 857]], "text_content": "\u8a31", "notation_coordinates": null, "notation_content": null}, {"box_type": "Music", "is_excluded_from_dataset": false, "is_line_break": false, "text_coordinates": [[504, 863], [560, 904]], "text_content": "\u6173", "notation_coordinates": null, "notation_content": null}, {"box_type": "Music", "is_excluded_from_dataset": false, "is_line_break": false, "text_coordinates": [[505, 911], [558, 948]], "text_content": "\u5c0f", "notation_coordinates": null, "notation_content": null}, {"box_type": "Music", "is_excluded_from_dataset": false, "is_line_break": true, "text_coordinates": [[505, 953], [557, 1000]], "text_content": "\u9072", "notation_coordinates": null, "notation_content": null}, {"box_type": "Music", "is_excluded_from_dataset": false, "is_line_break": false, "text_coordinates": [[433, 17], [492, 61]], "text_content": "\u6625", "notation_coordinates": null, "notation_content": null}, {"box_type": "Music", "is_excluded_from_dataset": false, "is_line_break": false, "text_coordinates": [[439, 71], [491, 104]], "text_content": "\u5fc3", "notation_coordinates": null, "notation_content": null}, {"box_type": "Music", "is_excluded_from_dataset": false, "is_line_break": true, "text_coordinates": [[436, 114], [495, 157]], "text_content": "\u900f", "notation_coordinates": null, "notation_content": null}]}