{"version": "2.0", "notation_type": "Text", "composer": "\u59dc\u5914", "mode_properties": {"gong_lvlv": "None", "final_note": "None"}, "images": ["../../images/siku_edition_070.png", "../../images/siku_edition_071.png", "../../images/siku_edition_072.png"], "content": [{"box_type": "Title", "is_excluded_from_dataset": false, "is_line_break": false, "text_coordinates": [[1926, 205], [1982, 253]], "text_content": "\u6eff"}, {"box_type": "Title", "is_excluded_from_dataset": false, "is_line_break": false, "text_coordinates": [[1929, 267], [1987, 300]], "text_content": "\u6c5f"}, {"box_type": "Title", "is_excluded_from_dataset": false, "is_line_break": true, "text_coordinates": [[1931, 314], [1989, 356]], "text_content": "\u7d05"}, {"box_type": "Preface", "is_excluded_from_dataset": false, "is_line_break": false, "text_coordinates": [[1838, 256], [1901, 303]], "text_content": "\u6eff"}, {"box_type": "Preface", "is_excluded_from_dataset": false, "is_line_break": false, "text_coordinates": [[1836, 319], [1896, 355]], "text_content": "\u6c5f"}, {"box_type": "Preface", "is_excluded_from_dataset": false, "is_line_break": false, "text_coordinates": [[1839, 370], [1896, 404]], "text_content": "\u7d05"}, {"box_type": "Preface", "is_excluded_from_dataset": false, "is_line_break": false, "text_coordinates": [[1842, 411], [1886, 469]], "text_content": "\u820a"}, {"box_type": "Preface", "is_excluded_from_dataset": false, "is_line_break": false, "text_coordinates": [[1835, 475], [1890, 515]], "text_content": "\u8abf"}, {"box_type": "Preface", "is_excluded_from_dataset": false, "is_line_break": false, "text_coordinates": [[1844, 522], [1883, 566]], "text_content": "\u7528"}, {"box_type": "Preface", "is_excluded_from_dataset": false, "is_line_break": false, "text_coordinates": [[1840, 574], [1896, 610]], "text_content": "\u4ec4"}, {"box_type": "Preface", "is_excluded_from_dataset": false, "is_line_break": false, "text_coordinates": [[1835, 620], [1893, 668]], "text_content": "\u97fb"}, {"box_type": "Preface", "is_excluded_from_dataset": false, "is_line_break": false, "text_coordinates": [[1848, 672], [1880, 720]], "text_content": "\u591a"}, {"box_type": "Preface", "is_excluded_from_dataset": false, "is_line_break": false, "text_coordinates": [[1841, 729], [1892, 763]], "text_content": "\u4e0d"}, {"box_type": "Preface", "is_excluded_from_dataset": false, "is_line_break": false, "text_coordinates": [[1843, 774], [1894, 818]], "text_content": "\u604a"}, {"box_type": "Preface", "is_excluded_from_dataset": false, "is_line_break": false, "text_coordinates": [[1841, 821], [1894, 874]], "text_content": "\u5f8b"}, {"box_type": "Preface", "is_excluded_from_dataset": false, "is_line_break": false, "text_coordinates": [[1835, 882], [1897, 914]], "text_content": "\u5982"}, {"box_type": "Preface", "is_excluded_from_dataset": false, "is_line_break": false, "text_coordinates": [[1848, 924], [1904, 969]], "text_content": "\u672b"}, {"box_type": "Preface", "is_excluded_from_dataset": false, "is_line_break": false, "text_coordinates": [[1854, 978], [1894, 1020]], "text_content": "\u53e5"}, {"box_type": "Preface", "is_excluded_from_dataset": false, "is_line_break": false, "text_coordinates": [[1847, 1030], [1894, 1067]], "text_content": "\u4e91"}, {"box_type": "Preface", "is_excluded_from_dataset": false, "is_line_break": true, "text_coordinates": [[1839, 1080], [1900, 1121]], "text_content": "\u7121"}, {"box_type": "Preface", "is_excluded_from_dataset": false, "is_line_break": false, "text_coordinates": [[1749, 266], [1794, 293]], "text_content": "\u5fc3"}, {"box_type": "Preface", "is_excluded_from_dataset": false, "is_line_break": false, "text_coordinates": [[1745, 313], [1797, 361]], "text_content": "\u64b2"}, {"box_type": "Preface", "is_excluded_from_dataset": false, "is_line_break": false, "text_coordinates": [[1749, 370], [1795, 403]], "text_content": "\u4e09"}, {"box_type": "Preface", "is_excluded_from_dataset": false, "is_line_break": false, "text_coordinates": [[1750, 414], [1793, 463]], "text_content": "\u5b57"}, {"box_type": "Preface", "is_excluded_from_dataset": false, "is_line_break": false, "text_coordinates": [[1743, 468], [1809, 515]], "text_content": "\u6b4c"}, {"box_type": "Preface", "is_excluded_from_dataset": false, "is_line_break": false, "text_coordinates": [[1746, 517], [1797, 561]], "text_content": "\u8005"}, {"box_type": "Preface", "is_excluded_from_dataset": false, "is_line_break": false, "text_coordinates": [[1750, 570], [1799, 616]], "text_content": "\u5c07"}, {"box_type": "Preface", "is_excluded_from_dataset": false, "is_line_break": false, "text_coordinates": [[1752, 626], [1798, 653]], "text_content": "\u5fc3"}, {"box_type": "Preface", "is_excluded_from_dataset": false, "is_line_break": false, "text_coordinates": [[1750, 669], [1794, 721]], "text_content": "\u5b57"}, {"box_type": "Preface", "is_excluded_from_dataset": false, "is_line_break": false, "text_coordinates": [[1750, 727], [1803, 766]], "text_content": "\u878d"}, {"box_type": "Preface", "is_excluded_from_dataset": false, "is_line_break": false, "text_coordinates": [[1746, 781], [1810, 811]], "text_content": "\u5165"}, {"box_type": "Preface", "is_excluded_from_dataset": false, "is_line_break": false, "text_coordinates": [[1751, 820], [1798, 863]], "text_content": "\u53bb"}, {"box_type": "Preface", "is_excluded_from_dataset": false, "is_line_break": false, "text_coordinates": [[1750, 870], [1802, 928]], "text_content": "\u8072"}, {"box_type": "Preface", "is_excluded_from_dataset": false, "is_line_break": false, "text_coordinates": [[1751, 932], [1801, 972]], "text_content": "\u65b9"}, {"box_type": "Preface", "is_excluded_from_dataset": false, "is_line_break": false, "text_coordinates": [[1745, 977], [1807, 1021]], "text_content": "\u8ae7"}, {"box_type": "Preface", "is_excluded_from_dataset": false, "is_line_break": false, "text_coordinates": [[1754, 1028], [1804, 1074]], "text_content": "\u97f3"}, {"box_type": "Preface", "is_excluded_from_dataset": false, "is_line_break": true, "text_coordinates": [[1755, 1077], [1808, 1125]], "text_content": "\u5f8b"}, {"box_type": "Preface", "is_excluded_from_dataset": false, "is_line_break": false, "text_coordinates": [[1659, 263], [1704, 311]], "text_content": "\u4e88"}, {"box_type": "Preface", "is_excluded_from_dataset": false, "is_line_break": false, "text_coordinates": [[1651, 316], [1717, 362]], "text_content": "\u6b32"}, {"box_type": "Preface", "is_excluded_from_dataset": false, "is_line_break": false, "text_coordinates": [[1658, 372], [1707, 402]], "text_content": "\u4ee5"}, {"box_type": "Preface", "is_excluded_from_dataset": false, "is_line_break": false, "text_coordinates": [[1655, 418], [1704, 462]], "text_content": "\u5e73"}, {"box_type": "Preface", "is_excluded_from_dataset": false, "is_line_break": false, "text_coordinates": [[1650, 469], [1705, 512]], "text_content": "\u97fb"}, {"box_type": "Preface", "is_excluded_from_dataset": false, "is_line_break": false, "text_coordinates": [[1666, 521], [1711, 572]], "text_content": "\u70ba"}, {"box_type": "Preface", "is_excluded_from_dataset": false, "is_line_break": false, "text_coordinates": [[1658, 578], [1714, 612]], "text_content": "\u4e4b"}, {"box_type": "Preface", "is_excluded_from_dataset": false, "is_line_break": false, "text_coordinates": [[1660, 625], [1713, 661]], "text_content": "\u4e45"}, {"box_type": "Preface", "is_excluded_from_dataset": false, "is_line_break": false, "text_coordinates": [[1659, 676], [1707, 709]], "text_content": "\u4e0d"}, {"box_type": "Preface", "is_excluded_from_dataset": false, "is_line_break": false, "text_coordinates": [[1661, 723], [1714, 765]], "text_content": "\u80fd"}, {"box_type": "Preface", "is_excluded_from_dataset": false, "is_line_break": false, "text_coordinates": [[1666, 771], [1716, 821]], "text_content": "\u6210"}, {"box_type": "Preface", "is_excluded_from_dataset": false, "is_line_break": false, "text_coordinates": [[1670, 828], [1703, 866]], "text_content": "\u56e0"}, {"box_type": "Preface", "is_excluded_from_dataset": false, "is_line_break": false, "text_coordinates": [[1659, 877], [1717, 917]], "text_content": "\u6cdb"}, {"box_type": "Preface", "is_excluded_from_dataset": false, "is_line_break": false, "text_coordinates": [[1665, 922], [1718, 975]], "text_content": "\u5de2"}, {"box_type": "Preface", "is_excluded_from_dataset": false, "is_line_break": false, "text_coordinates": [[1658, 980], [1710, 1021]], "text_content": "\u6e56"}, {"box_type": "Preface", "is_excluded_from_dataset": false, "is_line_break": false, "text_coordinates": [[1668, 1028], [1710, 1077]], "text_content": "\u805e"}, {"box_type": "Preface", "is_excluded_from_dataset": false, "is_line_break": true, "text_coordinates": [[1663, 1078], [1720, 1126]], "text_content": "\u903a"}, {"box_type": "Preface", "is_excluded_from_dataset": false, "is_line_break": false, "text_coordinates": [[1498, 256], [1542, 312]], "text_content": "\u5cb8"}, {"box_type": "Preface", "is_excluded_from_dataset": false, "is_line_break": false, "text_coordinates": [[1499, 316], [1550, 369]], "text_content": "\u7c2b"}, {"box_type": "Preface", "is_excluded_from_dataset": false, "is_line_break": false, "text_coordinates": [[1501, 370], [1562, 416]], "text_content": "\u9f13"}, {"box_type": "Preface", "is_excluded_from_dataset": false, "is_line_break": false, "text_coordinates": [[1500, 416], [1555, 474]], "text_content": "\u8072"}, {"box_type": "Preface", "is_excluded_from_dataset": false, "is_line_break": false, "text_coordinates": [[1508, 477], [1551, 524]], "text_content": "\u554f"}, {"box_type": "Preface", "is_excluded_from_dataset": false, "is_line_break": false, "text_coordinates": [[1502, 527], [1557, 566]], "text_content": "\u4e4b"}, {"box_type": "Preface", "is_excluded_from_dataset": false, "is_line_break": false, "text_coordinates": [[1502, 570], [1554, 614]], "text_content": "\u821f"}, {"box_type": "Preface", "is_excluded_from_dataset": false, "is_line_break": false, "text_coordinates": [[1508, 624], [1555, 672]], "text_content": "\u5e2b"}, {"box_type": "Preface", "is_excluded_from_dataset": false, "is_line_break": false, "text_coordinates": [[1505, 682], [1552, 716]], "text_content": "\u4e91"}, {"box_type": "Preface", "is_excluded_from_dataset": false, "is_line_break": false, "text_coordinates": [[1501, 729], [1546, 773]], "text_content": "\u5c45"}, {"box_type": "Preface", "is_excluded_from_dataset": false, "is_line_break": false, "text_coordinates": [[1505, 782], [1562, 821]], "text_content": "\u4eba"}, {"box_type": "Preface", "is_excluded_from_dataset": false, "is_line_break": false, "text_coordinates": [[1509, 830], [1557, 882]], "text_content": "\u70ba"}, {"box_type": "Preface", "is_excluded_from_dataset": false, "is_line_break": false, "text_coordinates": [[1506, 889], [1564, 924]], "text_content": "\u6b64"}, {"box_type": "Preface", "is_excluded_from_dataset": false, "is_line_break": false, "text_coordinates": [[1504, 936], [1557, 982]], "text_content": "\u6e56"}, {"box_type": "Preface", "is_excluded_from_dataset": false, "is_line_break": false, "text_coordinates": [[1504, 990], [1557, 1043]], "text_content": "\u795e"}, {"box_type": "Preface", "is_excluded_from_dataset": false, "is_line_break": false, "text_coordinates": [[1502, 1043], [1563, 1087]], "text_content": "\u59e5"}, {"box_type": "Preface", "is_excluded_from_dataset": false, "is_line_break": true, "text_coordinates": [[1506, 1090], [1558, 1144]], "text_content": "\u5900"}, {"box_type": "Preface", "is_excluded_from_dataset": false, "is_line_break": false, "text_coordinates": [[1406, 256], [1464, 292]], "text_content": "\u4e5f"}, {"box_type": "Preface", "is_excluded_from_dataset": false, "is_line_break": false, "text_coordinates": [[1410, 310], [1454, 358]], "text_content": "\u4e88"}, {"box_type": "Preface", "is_excluded_from_dataset": false, "is_line_break": false, "text_coordinates": [[1418, 367], [1455, 406]], "text_content": "\u56e0"}, {"box_type": "Preface", "is_excluded_from_dataset": false, "is_line_break": false, "text_coordinates": [[1406, 417], [1472, 459]], "text_content": "\u795d"}, {"box_type": "Preface", "is_excluded_from_dataset": false, "is_line_break": false, "text_coordinates": [[1419, 472], [1455, 500]], "text_content": "\u66f0"}, {"box_type": "Preface", "is_excluded_from_dataset": false, "is_line_break": false, "text_coordinates": [[1408, 519], [1464, 569]], "text_content": "\u5f97"}, {"box_type": "Preface", "is_excluded_from_dataset": false, "is_line_break": false, "text_coordinates": [[1413, 584], [1457, 592]], "text_content": "\u4e00"}, {"box_type": "Preface", "is_excluded_from_dataset": false, "is_line_break": false, "text_coordinates": [[1405, 619], [1453, 674]], "text_content": "\u5e2d"}, {"box_type": "Preface", "is_excluded_from_dataset": false, "is_line_break": false, "text_coordinates": [[1410, 681], [1470, 722]], "text_content": "\u98a8"}, {"box_type": "Preface", "is_excluded_from_dataset": false, "is_line_break": false, "text_coordinates": [[1410, 730], [1462, 770]], "text_content": "\u5f91"}, {"box_type": "Preface", "is_excluded_from_dataset": false, "is_line_break": false, "text_coordinates": [[1411, 781], [1463, 822]], "text_content": "\u81f3"}, {"box_type": "Preface", "is_excluded_from_dataset": false, "is_line_break": false, "text_coordinates": [[1408, 835], [1455, 880]], "text_content": "\u5c45"}, {"box_type": "Preface", "is_excluded_from_dataset": false, "is_line_break": false, "text_coordinates": [[1416, 885], [1473, 939]], "text_content": "\u5de2"}, {"box_type": "Preface", "is_excluded_from_dataset": false, "is_line_break": false, "text_coordinates": [[1416, 943], [1463, 990]], "text_content": "\u7576"}, {"box_type": "Preface", "is_excluded_from_dataset": false, "is_line_break": false, "text_coordinates": [[1415, 1000], [1462, 1029]], "text_content": "\u4ee5"}, {"box_type": "Preface", "is_excluded_from_dataset": false, "is_line_break": false, "text_coordinates": [[1410, 1044], [1461, 1086]], "text_content": "\u5e73"}, {"box_type": "Preface", "is_excluded_from_dataset": false, "is_line_break": true, "text_coordinates": [[1412, 1094], [1468, 1142]], "text_content": "\u97fb"}, {"box_type": "Preface", "is_excluded_from_dataset": false, "is_line_break": false, "text_coordinates": [[1314, 251], [1370, 301]], "text_content": "\u6eff"}, {"box_type": "Preface", "is_excluded_from_dataset": false, "is_line_break": false, "text_coordinates": [[1313, 319], [1370, 350]], "text_content": "\u6c5f"}, {"box_type": "Preface", "is_excluded_from_dataset": false, "is_line_break": false, "text_coordinates": [[1316, 361], [1372, 405]], "text_content": "\u7d05"}, {"box_type": "Preface", "is_excluded_from_dataset": false, "is_line_break": false, "text_coordinates": [[1320, 411], [1371, 464]], "text_content": "\u70ba"}, {"box_type": "Preface", "is_excluded_from_dataset": false, "is_line_break": false, "text_coordinates": [[1316, 469], [1376, 515]], "text_content": "\u8fce"}, {"box_type": "Preface", "is_excluded_from_dataset": false, "is_line_break": false, "text_coordinates": [[1313, 519], [1373, 570]], "text_content": "\u9001"}, {"box_type": "Preface", "is_excluded_from_dataset": false, "is_line_break": false, "text_coordinates": [[1315, 574], [1368, 625]], "text_content": "\u795e"}, {"box_type": "Preface", "is_excluded_from_dataset": false, "is_line_break": false, "text_coordinates": [[1325, 625], [1364, 664]], "text_content": "\u66f2"}, {"box_type": "Preface", "is_excluded_from_dataset": false, "is_line_break": false, "text_coordinates": [[1315, 677], [1361, 721]], "text_content": "\u8a00"}, {"box_type": "Preface", "is_excluded_from_dataset": false, "is_line_break": false, "text_coordinates": [[1314, 727], [1373, 772]], "text_content": "\u8a16"}, {"box_type": "Preface", "is_excluded_from_dataset": false, "is_line_break": false, "text_coordinates": [[1319, 782], [1376, 824]], "text_content": "\u98a8"}, {"box_type": "Preface", "is_excluded_from_dataset": false, "is_line_break": false, "text_coordinates": [[1312, 834], [1369, 878]], "text_content": "\u8207"}, {"box_type": "Preface", "is_excluded_from_dataset": false, "is_line_break": false, "text_coordinates": [[1316, 886], [1368, 940]], "text_content": "\u7b46"}, {"box_type": "Preface", "is_excluded_from_dataset": false, "is_line_break": false, "text_coordinates": [[1317, 944], [1370, 986]], "text_content": "\u4ff1"}, {"box_type": "Preface", "is_excluded_from_dataset": false, "is_line_break": false, "text_coordinates": [[1320, 993], [1376, 1037]], "text_content": "\u99db"}, {"box_type": "Preface", "is_excluded_from_dataset": false, "is_line_break": false, "text_coordinates": [[1322, 1044], [1373, 1086]], "text_content": "\u9803"}, {"box_type": "Preface", "is_excluded_from_dataset": false, "is_line_break": true, "text_coordinates": [[1322, 1093], [1372, 1141]], "text_content": "\u523b"}, {"box_type": "Preface", "is_excluded_from_dataset": false, "is_line_break": false, "text_coordinates": [[1225, 261], [1276, 299]], "text_content": "\u800c"}, {"box_type": "Preface", "is_excluded_from_dataset": false, "is_line_break": false, "text_coordinates": [[1224, 306], [1284, 360]], "text_content": "\u6210"}, {"box_type": "Preface", "is_excluded_from_dataset": false, "is_line_break": false, "text_coordinates": [[1226, 360], [1282, 405]], "text_content": "\u672b"}, {"box_type": "Preface", "is_excluded_from_dataset": false, "is_line_break": false, "text_coordinates": [[1229, 416], [1271, 459]], "text_content": "\u53e5"}, {"box_type": "Preface", "is_excluded_from_dataset": false, "is_line_break": false, "text_coordinates": [[1225, 472], [1270, 506]], "text_content": "\u4e91"}, {"box_type": "Preface", "is_excluded_from_dataset": false, "is_line_break": false, "text_coordinates": [[1228, 519], [1273, 567]], "text_content": "\u805e"}, {"box_type": "Preface", "is_excluded_from_dataset": false, "is_line_break": false, "text_coordinates": [[1222, 574], [1286, 614]], "text_content": "\u73ee"}, {"box_type": "Preface", "is_excluded_from_dataset": false, "is_line_break": false, "text_coordinates": [[1221, 622], [1284, 668]], "text_content": "\u74b0"}, {"box_type": "Preface", "is_excluded_from_dataset": false, "is_line_break": false, "text_coordinates": [[1226, 676], [1270, 722]], "text_content": "\u5247"}, {"box_type": "Preface", "is_excluded_from_dataset": false, "is_line_break": false, "text_coordinates": [[1222, 724], [1279, 770]], "text_content": "\u5354"}, {"box_type": "Preface", "is_excluded_from_dataset": false, "is_line_break": false, "text_coordinates": [[1223, 776], [1278, 830]], "text_content": "\u5f8b"}, {"box_type": "Preface", "is_excluded_from_dataset": false, "is_line_break": false, "text_coordinates": [[1226, 832], [1277, 881]], "text_content": "\u77e3"}, {"box_type": "Preface", "is_excluded_from_dataset": false, "is_line_break": false, "text_coordinates": [[1226, 884], [1277, 935]], "text_content": "\u66f8"}, {"box_type": "Preface", "is_excluded_from_dataset": false, "is_line_break": false, "text_coordinates": [[1229, 948], [1274, 974]], "text_content": "\u4ee5"}, {"box_type": "Preface", "is_excluded_from_dataset": false, "is_line_break": false, "text_coordinates": [[1228, 988], [1279, 1032]], "text_content": "\u7dd1"}, {"box_type": "Preface", "is_excluded_from_dataset": false, "is_line_break": false, "text_coordinates": [[1231, 1039], [1279, 1095]], "text_content": "\u7b8b"}, {"box_type": "Preface", "is_excluded_from_dataset": false, "is_line_break": true, "text_coordinates": [[1226, 1095], [1287, 1140]], "text_content": "\u6c88"}, {"box_type": "Preface", "is_excluded_from_dataset": false, "is_line_break": false, "text_coordinates": [[1134, 257], [1172, 298]], "text_content": "\u4e8e"}, {"box_type": "Preface", "is_excluded_from_dataset": false, "is_line_break": false, "text_coordinates": [[1138, 309], [1177, 348]], "text_content": "\u767d"}, {"box_type": "Preface", "is_excluded_from_dataset": false, "is_line_break": false, "text_coordinates": [[1132, 361], [1193, 407]], "text_content": "\u6d6a"}, {"box_type": "Preface", "is_excluded_from_dataset": false, "is_line_break": false, "text_coordinates": [[1130, 414], [1179, 460]], "text_content": "\u8f9b"}, {"box_type": "Preface", "is_excluded_from_dataset": false, "is_line_break": false, "text_coordinates": [[1134, 465], [1175, 512]], "text_content": "\u4ea5"}, {"box_type": "Preface", "is_excluded_from_dataset": false, "is_line_break": false, "text_coordinates": [[1125, 522], [1180, 559]], "text_content": "\u6b63"}, {"box_type": "Preface", "is_excluded_from_dataset": false, "is_line_break": false, "text_coordinates": [[1134, 571], [1169, 613]], "text_content": "\u6708"}, {"box_type": "Preface", "is_excluded_from_dataset": false, "is_line_break": false, "text_coordinates": [[1135, 622], [1187, 670]], "text_content": "\u6666"}, {"box_type": "Preface", "is_excluded_from_dataset": false, "is_line_break": false, "text_coordinates": [[1128, 676], [1190, 715]], "text_content": "\u4e5f"}, {"box_type": "Preface", "is_excluded_from_dataset": false, "is_line_break": false, "text_coordinates": [[1129, 726], [1189, 776]], "text_content": "\u662f"}, {"box_type": "Preface", "is_excluded_from_dataset": false, "is_line_break": false, "text_coordinates": [[1133, 779], [1193, 833]], "text_content": "\u6b72"}, {"box_type": "Preface", "is_excluded_from_dataset": false, "is_line_break": false, "text_coordinates": [[1131, 835], [1181, 867]], "text_content": "\u516d"}, {"box_type": "Preface", "is_excluded_from_dataset": false, "is_line_break": false, "text_coordinates": [[1135, 886], [1167, 927]], "text_content": "\u6708"}, {"box_type": "Preface", "is_excluded_from_dataset": false, "is_line_break": false, "text_coordinates": [[1134, 935], [1196, 987]], "text_content": "\u5fa9"}, {"box_type": "Preface", "is_excluded_from_dataset": false, "is_line_break": false, "text_coordinates": [[1135, 991], [1193, 1040]], "text_content": "\u904e"}, {"box_type": "Preface", "is_excluded_from_dataset": false, "is_line_break": false, "text_coordinates": [[1131, 1046], [1186, 1089]], "text_content": "\u7960"}, {"box_type": "Preface", "is_excluded_from_dataset": false, "is_line_break": true, "text_coordinates": [[1137, 1104], [1186, 1144]], "text_content": "\u4e0b"}, {"box_type": "Preface", "is_excluded_from_dataset": false, "is_line_break": false, "text_coordinates": [[1044, 259], [1084, 298]], "text_content": "\u56e0"}, {"box_type": "Preface", "is_excluded_from_dataset": false, "is_line_break": false, "text_coordinates": [[1035, 310], [1087, 355]], "text_content": "\u523b"}, {"box_type": "Preface", "is_excluded_from_dataset": false, "is_line_break": false, "text_coordinates": [[1037, 366], [1096, 404]], "text_content": "\u4e4b"}, {"box_type": "Preface", "is_excluded_from_dataset": false, "is_line_break": false, "text_coordinates": [[1032, 412], [1093, 454]], "text_content": "\u67f1"}, {"box_type": "Preface", "is_excluded_from_dataset": false, "is_line_break": false, "text_coordinates": [[1042, 465], [1086, 514]], "text_content": "\u9593"}, {"box_type": "Preface", "is_excluded_from_dataset": false, "is_line_break": false, "text_coordinates": [[1035, 518], [1083, 565]], "text_content": "\u6709"}, {"box_type": "Preface", "is_excluded_from_dataset": false, "is_line_break": false, "text_coordinates": [[1039, 570], [1095, 615]], "text_content": "\u5ba2"}, {"box_type": "Preface", "is_excluded_from_dataset": false, "is_line_break": false, "text_coordinates": [[1038, 621], [1095, 671]], "text_content": "\u4f86"}, {"box_type": "Preface", "is_excluded_from_dataset": false, "is_line_break": false, "text_coordinates": [[1040, 677], [1077, 722]], "text_content": "\u81ea"}, {"box_type": "Preface", "is_excluded_from_dataset": false, "is_line_break": false, "text_coordinates": [[1034, 726], [1079, 772]], "text_content": "\u5c45"}, {"box_type": "Preface", "is_excluded_from_dataset": false, "is_line_break": false, "text_coordinates": [[1041, 777], [1095, 832]], "text_content": "\u5de2"}, {"box_type": "Preface", "is_excluded_from_dataset": false, "is_line_break": false, "text_coordinates": [[1039, 840], [1084, 876]], "text_content": "\u4e91"}, {"box_type": "Preface", "is_excluded_from_dataset": false, "is_line_break": false, "text_coordinates": [[1035, 886], [1089, 922]], "text_content": "\u571f"}, {"box_type": "Preface", "is_excluded_from_dataset": false, "is_line_break": false, "text_coordinates": [[1038, 939], [1099, 977]], "text_content": "\u4eba"}, {"box_type": "Preface", "is_excluded_from_dataset": false, "is_line_break": false, "text_coordinates": [[1040, 992], [1091, 1038]], "text_content": "\u7960"}, {"box_type": "Preface", "is_excluded_from_dataset": false, "is_line_break": false, "text_coordinates": [[1035, 1041], [1101, 1084]], "text_content": "\u59e5"}, {"box_type": "Preface", "is_excluded_from_dataset": false, "is_line_break": true, "text_coordinates": [[1039, 1094], [1105, 1136]], "text_content": "\u8f19"}, {"box_type": "Preface", "is_excluded_from_dataset": false, "is_line_break": false, "text_coordinates": [[940, 254], [1001, 302]], "text_content": "\u80fd"}, {"box_type": "Preface", "is_excluded_from_dataset": false, "is_line_break": false, "text_coordinates": [[941, 312], [1004, 357]], "text_content": "\u6b4c"}, {"box_type": "Preface", "is_excluded_from_dataset": false, "is_line_break": false, "text_coordinates": [[946, 364], [1002, 402]], "text_content": "\u6b64"}, {"box_type": "Preface", "is_excluded_from_dataset": false, "is_line_break": false, "text_coordinates": [[942, 417], [996, 461]], "text_content": "\u8a5e"}, {"box_type": "Preface", "is_excluded_from_dataset": false, "is_line_break": false, "text_coordinates": [[942, 467], [997, 512]], "text_content": "\u6309"}, {"box_type": "Preface", "is_excluded_from_dataset": false, "is_line_break": false, "text_coordinates": [[951, 516], [990, 569]], "text_content": "\u66f9"}, {"box_type": "Preface", "is_excluded_from_dataset": false, "is_line_break": false, "text_coordinates": [[943, 571], [998, 618]], "text_content": "\u64cd"}, {"box_type": "Preface", "is_excluded_from_dataset": false, "is_line_break": false, "text_coordinates": [[941, 625], [996, 666]], "text_content": "\u81f3"}, {"box_type": "Preface", "is_excluded_from_dataset": false, "is_line_break": false, "text_coordinates": [[939, 679], [995, 725]], "text_content": "\u6fe1"}, {"box_type": "Preface", "is_excluded_from_dataset": false, "is_line_break": false, "text_coordinates": [[941, 733], [997, 781]], "text_content": "\u9808"}, {"box_type": "Preface", "is_excluded_from_dataset": false, "is_line_break": false, "text_coordinates": [[958, 789], [985, 812]], "text_content": "\u53e3"}, {"box_type": "Preface", "is_excluded_from_dataset": false, "is_line_break": false, "text_coordinates": [[943, 829], [997, 876]], "text_content": "\u5b6b"}, {"box_type": "Preface", "is_excluded_from_dataset": false, "is_line_break": false, "text_coordinates": [[939, 881], [998, 930]], "text_content": "\u6b0a"}, {"box_type": "Preface", "is_excluded_from_dataset": false, "is_line_break": false, "text_coordinates": [[947, 937], [1002, 990]], "text_content": "\u907a"}, {"box_type": "Preface", "is_excluded_from_dataset": false, "is_line_break": false, "text_coordinates": [[946, 991], [1002, 1038]], "text_content": "\u64cd"}, {"box_type": "Preface", "is_excluded_from_dataset": false, "is_line_break": false, "text_coordinates": [[947, 1042], [1000, 1093]], "text_content": "\u66f8"}, {"box_type": "Preface", "is_excluded_from_dataset": false, "is_line_break": true, "text_coordinates": [[958, 1102], [997, 1135]], "text_content": "\u66f0"}, {"box_type": "Preface", "is_excluded_from_dataset": false, "is_line_break": false, "text_coordinates": [[846, 256], [911, 302]], "text_content": "\u6625"}, {"box_type": "Preface", "is_excluded_from_dataset": false, "is_line_break": false, "text_coordinates": [[850, 312], [909, 355]], "text_content": "\u6c34"}, {"box_type": "Preface", "is_excluded_from_dataset": false, "is_line_break": false, "text_coordinates": [[849, 363], [901, 405]], "text_content": "\u65b9"}, {"box_type": "Preface", "is_excluded_from_dataset": false, "is_line_break": false, "text_coordinates": [[852, 415], [903, 453]], "text_content": "\u751f"}, {"box_type": "Preface", "is_excluded_from_dataset": false, "is_line_break": false, "text_coordinates": [[852, 470], [910, 506]], "text_content": "\u516c"}, {"box_type": "Preface", "is_excluded_from_dataset": false, "is_line_break": false, "text_coordinates": [[854, 519], [896, 561]], "text_content": "\u5b9c"}, {"box_type": "Preface", "is_excluded_from_dataset": false, "is_line_break": false, "text_coordinates": [[848, 572], [907, 620]], "text_content": "\u901f"}, {"box_type": "Preface", "is_excluded_from_dataset": false, "is_line_break": false, "text_coordinates": [[849, 623], [898, 666]], "text_content": "\u53bb"}, {"box_type": "Preface", "is_excluded_from_dataset": false, "is_line_break": false, "text_coordinates": [[848, 677], [903, 723]], "text_content": "\u64cd"}, {"box_type": "Preface", "is_excluded_from_dataset": false, "is_line_break": false, "text_coordinates": [[859, 735], [895, 760]], "text_content": "\u66f0"}, {"box_type": "Preface", "is_excluded_from_dataset": false, "is_line_break": false, "text_coordinates": [[849, 774], [905, 822]], "text_content": "\u5b6b"}, {"box_type": "Preface", "is_excluded_from_dataset": false, "is_line_break": false, "text_coordinates": [[849, 827], [904, 878]], "text_content": "\u6b0a"}, {"box_type": "Preface", "is_excluded_from_dataset": false, "is_line_break": false, "text_coordinates": [[850, 889], [901, 925]], "text_content": "\u4e0d"}, {"box_type": "Preface", "is_excluded_from_dataset": false, "is_line_break": false, "text_coordinates": [[849, 932], [915, 985]], "text_content": "\u6b3a"}, {"box_type": "Preface", "is_excluded_from_dataset": false, "is_line_break": false, "text_coordinates": [[854, 989], [919, 1033]], "text_content": "\u5b64"}, {"box_type": "Preface", "is_excluded_from_dataset": false, "is_line_break": false, "text_coordinates": [[858, 1045], [905, 1088]], "text_content": "\u4e43"}, {"box_type": "Preface", "is_excluded_from_dataset": false, "is_line_break": true, "text_coordinates": [[853, 1095], [921, 1139]], "text_content": "\u5fb9"}, {"box_type": "Preface", "is_excluded_from_dataset": false, "is_line_break": false, "text_coordinates": [[701, 260], [742, 307]], "text_content": "\u8ecd"}, {"box_type": "Preface", "is_excluded_from_dataset": false, "is_line_break": false, "text_coordinates": [[695, 314], [751, 360]], "text_content": "\u9084"}, {"box_type": "Preface", "is_excluded_from_dataset": false, "is_line_break": false, "text_coordinates": [[692, 363], [747, 409]], "text_content": "\u6fe1"}, {"box_type": "Preface", "is_excluded_from_dataset": false, "is_line_break": false, "text_coordinates": [[699, 414], [747, 455]], "text_content": "\u9808"}, {"box_type": "Preface", "is_excluded_from_dataset": false, "is_line_break": false, "text_coordinates": [[713, 467], [737, 490]], "text_content": "\u53e3"}, {"box_type": "Preface", "is_excluded_from_dataset": false, "is_line_break": false, "text_coordinates": [[693, 510], [748, 555]], "text_content": "\u8207"}, {"box_type": "Preface", "is_excluded_from_dataset": false, "is_line_break": false, "text_coordinates": [[700, 561], [752, 611]], "text_content": "\u6771"}, {"box_type": "Preface", "is_excluded_from_dataset": false, "is_line_break": false, "text_coordinates": [[704, 613], [746, 662]], "text_content": "\u95dc"}, {"box_type": "Preface", "is_excluded_from_dataset": false, "is_line_break": false, "text_coordinates": [[697, 668], [746, 709]], "text_content": "\u76f8"}, {"box_type": "Preface", "is_excluded_from_dataset": false, "is_line_break": false, "text_coordinates": [[701, 715], [756, 764]], "text_content": "\u8fd1"}, {"box_type": "Preface", "is_excluded_from_dataset": false, "is_line_break": false, "text_coordinates": [[697, 773], [752, 806]], "text_content": "\u6c5f"}, {"box_type": "Preface", "is_excluded_from_dataset": false, "is_line_break": false, "text_coordinates": [[697, 813], [751, 857]], "text_content": "\u6e56"}, {"box_type": "Preface", "is_excluded_from_dataset": false, "is_line_break": false, "text_coordinates": [[703, 867], [762, 907]], "text_content": "\u6c34"}, {"box_type": "Preface", "is_excluded_from_dataset": false, "is_line_break": false, "text_coordinates": [[701, 920], [760, 958]], "text_content": "\u4e4b"}, {"box_type": "Preface", "is_excluded_from_dataset": false, "is_line_break": false, "text_coordinates": [[709, 967], [757, 1013]], "text_content": "\u6240"}, {"box_type": "Preface", "is_excluded_from_dataset": false, "is_line_break": false, "text_coordinates": [[710, 1017], [747, 1059]], "text_content": "\u51fa"}, {"box_type": "Preface", "is_excluded_from_dataset": false, "is_line_break": true, "text_coordinates": [[705, 1077], [762, 1106]], "text_content": "\u5165"}, {"box_type": "Preface", "is_excluded_from_dataset": false, "is_line_break": false, "text_coordinates": [[607, 258], [652, 305]], "text_content": "\u4e88"}, {"box_type": "Preface", "is_excluded_from_dataset": false, "is_line_break": false, "text_coordinates": [[605, 310], [654, 358]], "text_content": "\u610f"}, {"box_type": "Preface", "is_excluded_from_dataset": false, "is_line_break": false, "text_coordinates": [[602, 359], [666, 406]], "text_content": "\u6625"}, {"box_type": "Preface", "is_excluded_from_dataset": false, "is_line_break": false, "text_coordinates": [[605, 413], [665, 452]], "text_content": "\u6c34"}, {"box_type": "Preface", "is_excluded_from_dataset": false, "is_line_break": false, "text_coordinates": [[606, 462], [656, 503]], "text_content": "\u65b9"}, {"box_type": "Preface", "is_excluded_from_dataset": false, "is_line_break": false, "text_coordinates": [[606, 512], [656, 553]], "text_content": "\u751f"}, {"box_type": "Preface", "is_excluded_from_dataset": false, "is_line_break": false, "text_coordinates": [[607, 565], [663, 605]], "text_content": "\u5fc5"}, {"box_type": "Preface", "is_excluded_from_dataset": false, "is_line_break": false, "text_coordinates": [[611, 615], [655, 661]], "text_content": "\u6709"}, {"box_type": "Preface", "is_excluded_from_dataset": false, "is_line_break": false, "text_coordinates": [[621, 668], [654, 708]], "text_content": "\u53f8"}, {"box_type": "Preface", "is_excluded_from_dataset": false, "is_line_break": false, "text_coordinates": [[610, 719], [667, 756]], "text_content": "\u4e4b"}, {"box_type": "Preface", "is_excluded_from_dataset": false, "is_line_break": false, "text_coordinates": [[606, 763], [660, 808]], "text_content": "\u8005"}, {"box_type": "Preface", "is_excluded_from_dataset": false, "is_line_break": false, "text_coordinates": [[607, 813], [670, 855]], "text_content": "\u6545"}, {"box_type": "Preface", "is_excluded_from_dataset": false, "is_line_break": false, "text_coordinates": [[612, 863], [666, 914]], "text_content": "\u6b78"}, {"box_type": "Preface", "is_excluded_from_dataset": false, "is_line_break": false, "text_coordinates": [[611, 916], [663, 961]], "text_content": "\u5176"}, {"box_type": "Preface", "is_excluded_from_dataset": false, "is_line_break": false, "text_coordinates": [[615, 973], [664, 1002]], "text_content": "\u529f"}, {"box_type": "Preface", "is_excluded_from_dataset": false, "is_line_break": false, "text_coordinates": [[611, 1014], [674, 1057]], "text_content": "\u65bc"}, {"box_type": "Preface", "is_excluded_from_dataset": false, "is_line_break": true, "text_coordinates": [[607, 1071], [667, 1113]], "text_content": "\u59e5"}, {"box_type": "Preface", "is_excluded_from_dataset": false, "is_line_break": true, "text_coordinates": [[517, 261], [562, 299]], "text_content": "\u4e91"}, {"box_type": "Unmarked", "is_excluded_from_dataset": false, "is_line_break": false, "text_coordinates": [[365, 819], [399, 857]], "text_content": "\u5edf"}, {"box_type": "Unmarked", "is_excluded_from_dataset": false, "is_line_break": false, "text_coordinates": [[373, 869], [396, 902]], "text_content": "\u4e2d"}, {"box_type": "Unmarked", "is_excluded_from_dataset": false, "is_line_break": false, "text_coordinates": [[371, 919], [400, 954]], "text_content": "\u5217"}, {"box_type": "Unmarked", "is_excluded_from_dataset": false, "is_line_break": false, "text_coordinates": [[371, 967], [402, 997]], "text_content": "\u5750"}, {"box_type": "Unmarked", "is_excluded_from_dataset": false, "is_line_break": false, "text_coordinates": [[366, 1023], [405, 1049]], "text_content": "\u5982"}, {"box_type": "Unmarked", "is_excluded_from_dataset": false, "is_line_break": true, "text_coordinates": [[373, 1070], [407, 1106]], "text_content": "\u592b"}, {"box_type": "Unmarked", "is_excluded_from_dataset": false, "is_line_break": false, "text_coordinates": [[325, 822], [361, 845]], "text_content": "\u4eba"}, {"box_type": "Unmarked", "is_excluded_from_dataset": false, "is_line_break": false, "text_coordinates": [[326, 866], [359, 902]], "text_content": "\u8005"}, {"box_type": "Unmarked", "is_excluded_from_dataset": false, "is_line_break": false, "text_coordinates": [[327, 919], [358, 944]], "text_content": "\u5341"}, {"box_type": "Unmarked", "is_excluded_from_dataset": false, "is_line_break": false, "text_coordinates": [[328, 971], [360, 994]], "text_content": "\u4e09"}, {"box_type": "Unmarked", "is_excluded_from_dataset": false, "is_line_break": false, "text_coordinates": [[331, 1018], [366, 1047]], "text_content": "\u4eba"}, {"box_type": "Music", "is_excluded_from_dataset": false, "is_line_break": false, "text_coordinates": [[417, 50], [474, 88]], "text_content": "\u4ed9", "notation_coordinates": null, "notation_content": null}, {"box_type": "Music", "is_excluded_from_dataset": false, "is_line_break": false, "text_coordinates": [[419, 102], [482, 149]], "text_content": "\u59e5", "notation_coordinates": null, "notation_content": null}, {"box_type": "Music", "is_excluded_from_dataset": false, "is_line_break": false, "text_coordinates": [[427, 149], [486, 199]], "text_content": "\u4f86", "notation_coordinates": null, "notation_content": null}, {"box_type": "Music", "is_excluded_from_dataset": false, "is_line_break": false, "text_coordinates": [[430, 203], [480, 257]], "text_content": "\u6642", "notation_coordinates": null, "notation_content": null}, {"box_type": "Music", "is_excluded_from_dataset": false, "is_line_break": false, "text_coordinates": [[425, 264], [474, 294]], "text_content": "\u6b63", "notation_coordinates": null, "notation_content": null}, {"box_type": "Music", "is_excluded_from_dataset": false, "is_line_break": false, "text_coordinates": [[427, 324], [474, 333]], "text_content": "\u4e00", "notation_coordinates": null, "notation_content": null}, {"box_type": "Music", "is_excluded_from_dataset": false, "is_line_break": false, "text_coordinates": [[431, 357], [475, 404]], "text_content": "\u671b", "notation_coordinates": null, "notation_content": null}, {"box_type": "Music", "is_excluded_from_dataset": false, "is_line_break": false, "text_coordinates": [[427, 412], [473, 456]], "text_content": "\u5343", "notation_coordinates": null, "notation_content": null}, {"box_type": "Music", "is_excluded_from_dataset": false, "is_line_break": false, "text_coordinates": [[429, 462], [474, 505]], "text_content": "\u9803", "notation_coordinates": null, "notation_content": null}, {"box_type": "Music", "is_excluded_from_dataset": false, "is_line_break": false, "text_coordinates": [[429, 510], [479, 568]], "text_content": "\u7fe0", "notation_coordinates": null, "notation_content": null}, {"box_type": "Music", "is_excluded_from_dataset": false, "is_line_break": false, "text_coordinates": [[426, 568], [480, 613]], "text_content": "\u703e", "notation_coordinates": null, "notation_content": null}, {"box_type": "Music", "is_excluded_from_dataset": false, "is_line_break": false, "text_coordinates": [[425, 614], [484, 657]], "text_content": "\u65cc", "notation_coordinates": null, "notation_content": null}, {"box_type": "Music", "is_excluded_from_dataset": false, "is_line_break": false, "text_coordinates": [[425, 663], [480, 709]], "text_content": "\u65d7", "notation_coordinates": null, "notation_content": null}, {"box_type": "Music", "is_excluded_from_dataset": false, "is_line_break": false, "text_coordinates": [[427, 716], [481, 756]], "text_content": "\u5171", "notation_coordinates": null, "notation_content": null}, {"box_type": "Music", "is_excluded_from_dataset": false, "is_line_break": false, "text_coordinates": [[431, 764], [487, 808]], "text_content": "\u4e82", "notation_coordinates": null, "notation_content": null}, {"box_type": "Music", "is_excluded_from_dataset": false, "is_line_break": false, "text_coordinates": [[433, 814], [479, 861]], "text_content": "\u96f2", "notation_coordinates": null, "notation_content": null}, {"box_type": "Music", "is_excluded_from_dataset": false, "is_line_break": false, "text_coordinates": [[432, 866], [483, 907]], "text_content": "\u4ff1", "notation_coordinates": null, "notation_content": null}, {"box_type": "Music", "is_excluded_from_dataset": false, "is_line_break": false, "text_coordinates": [[431, 919], [479, 957]], "text_content": "\u4e0b", "notation_coordinates": null, "notation_content": null}, {"box_type": "Music", "is_excluded_from_dataset": false, "is_line_break": false, "text_coordinates": [[427, 965], [496, 1010]], "text_content": "\u4f9d", "notation_coordinates": null, "notation_content": null}, {"box_type": "Music", "is_excluded_from_dataset": false, "is_line_break": false, "text_coordinates": [[433, 1017], [483, 1060]], "text_content": "\u7d04", "notation_coordinates": null, "notation_content": null}, {"box_type": "Music", "is_excluded_from_dataset": false, "is_line_break": true, "text_coordinates": [[431, 1065], [480, 1113]], "text_content": "\u524d", "notation_coordinates": null, "notation_content": null}, {"box_type": "Music", "is_excluded_from_dataset": false, "is_line_break": false, "text_coordinates": [[335, 50], [376, 85]], "text_content": "\u5c71", "notation_coordinates": null, "notation_content": null}, {"box_type": "Music", "is_excluded_from_dataset": false, "is_line_break": false, "text_coordinates": [[329, 98], [391, 145]], "text_content": "\u547d", "notation_coordinates": null, "notation_content": null}, {"box_type": "Music", "is_excluded_from_dataset": false, "is_line_break": false, "text_coordinates": [[333, 151], [385, 205]], "text_content": "\u99d5", "notation_coordinates": null, "notation_content": null}, {"box_type": "Music", "is_excluded_from_dataset": false, "is_line_break": false, "text_coordinates": [[331, 207], [382, 262]], "text_content": "\u7fa3", "notation_coordinates": null, "notation_content": null}, {"box_type": "Music", "is_excluded_from_dataset": false, "is_line_break": false, "text_coordinates": [[331, 262], [394, 309]], "text_content": "\u9f8d", "notation_coordinates": null, "notation_content": null}, {"box_type": "Music", "is_excluded_from_dataset": false, "is_line_break": false, "text_coordinates": [[335, 313], [396, 353]], "text_content": "\u91d1", "notation_coordinates": null, "notation_content": null}, {"box_type": "Music", "is_excluded_from_dataset": false, "is_line_break": false, "text_coordinates": [[337, 362], [388, 404]], "text_content": "\u4f5c", "notation_coordinates": null, "notation_content": null}, {"box_type": "Music", "is_excluded_from_dataset": false, "is_line_break": false, "text_coordinates": [[335, 410], [395, 449]], "text_content": "\u8edb", "notation_coordinates": null, "notation_content": null}, {"box_type": "Music", "is_excluded_from_dataset": false, "is_line_break": false, "text_coordinates": [[335, 461], [386, 500]], "text_content": "\u76f8", "notation_coordinates": null, "notation_content": null}, {"box_type": "Music", "is_excluded_from_dataset": false, "is_line_break": false, "text_coordinates": [[336, 510], [397, 557]], "text_content": "\u5f9e", "notation_coordinates": null, "notation_content": null}, {"box_type": "Music", "is_excluded_from_dataset": false, "is_line_break": false, "text_coordinates": [[331, 560], [386, 606]], "text_content": "\u8af8", "notation_coordinates": null, "notation_content": null}, {"box_type": "Music", "is_excluded_from_dataset": false, "is_line_break": false, "text_coordinates": [[329, 612], [389, 661]], "text_content": "\u5a23", "notation_coordinates": null, "notation_content": null}, {"box_type": "Music", "is_excluded_from_dataset": false, "is_line_break": false, "text_coordinates": [[337, 668], [387, 699]], "text_content": "\u7389", "notation_coordinates": null, "notation_content": null}, {"box_type": "Music", "is_excluded_from_dataset": false, "is_line_break": false, "text_coordinates": [[344, 711], [390, 762]], "text_content": "\u70ba", "notation_coordinates": null, "notation_content": null}, {"box_type": "Music", "is_excluded_from_dataset": false, "is_line_break": false, "text_coordinates": [[340, 767], [393, 805]], "text_content": "\u51a0", "notation_coordinates": null, "notation_content": null}, {"box_type": "Music", "is_excluded_from_dataset": false, "is_line_break": false, "text_coordinates": [[246, 49], [295, 90]], "text_content": "\u5411", "notation_coordinates": null, "notation_content": null}, {"box_type": "Music", "is_excluded_from_dataset": false, "is_line_break": false, "text_coordinates": [[238, 101], [305, 147]], "text_content": "\u591c", "notation_coordinates": null, "notation_content": null}, {"box_type": "Music", "is_excluded_from_dataset": false, "is_line_break": false, "text_coordinates": [[243, 155], [299, 199]], "text_content": "\u6df1", "notation_coordinates": null, "notation_content": null}, {"box_type": "Music", "is_excluded_from_dataset": false, "is_line_break": false, "text_coordinates": [[248, 206], [305, 250]], "text_content": "\u98a8", "notation_coordinates": null, "notation_content": null}, {"box_type": "Music", "is_excluded_from_dataset": false, "is_line_break": false, "text_coordinates": [[247, 256], [300, 299]], "text_content": "\u5b9a", "notation_coordinates": null, "notation_content": null}, {"box_type": "Music", "is_excluded_from_dataset": false, "is_line_break": false, "text_coordinates": [[246, 309], [296, 356]], "text_content": "\u6084", "notation_coordinates": null, "notation_content": null}, {"box_type": "Music", "is_excluded_from_dataset": false, "is_line_break": false, "text_coordinates": [[241, 359], [300, 403]], "text_content": "\u7121", "notation_coordinates": null, "notation_content": null}, {"box_type": "Music", "is_excluded_from_dataset": false, "is_line_break": false, "text_coordinates": [[242, 415], [304, 454]], "text_content": "\u4eba", "notation_coordinates": null, "notation_content": null}, {"box_type": "Music", "is_excluded_from_dataset": false, "is_line_break": false, "text_coordinates": [[252, 461], [296, 510]], "text_content": "\u805e", "notation_coordinates": null, "notation_content": null}, {"box_type": "Music", "is_excluded_from_dataset": false, "is_line_break": false, "text_coordinates": [[246, 514], [309, 555]], "text_content": "\u73ee", "notation_coordinates": null, "notation_content": null}, {"box_type": "Music", "is_excluded_from_dataset": false, "is_line_break": false, "text_coordinates": [[244, 561], [298, 607]], "text_content": "\u74b0", "notation_coordinates": null, "notation_content": null}, {"box_type": "Music", "is_excluded_from_dataset": false, "is_line_break": false, "text_coordinates": [[254, 614], [294, 652]], "text_content": " ", "notation_coordinates": null, "notation_content": null}, {"box_type": "Music", "is_excluded_from_dataset": false, "is_line_break": false, "text_coordinates": [[246, 663], [298, 709]], "text_content": "\u795e", "notation_coordinates": null, "notation_content": null}, {"box_type": "Music", "is_excluded_from_dataset": false, "is_line_break": false, "text_coordinates": [[249, 715], [299, 762]], "text_content": "\u7ad2", "notation_coordinates": null, "notation_content": null}, {"box_type": "Music", "is_excluded_from_dataset": false, "is_line_break": false, "text_coordinates": [[248, 766], [304, 814]], "text_content": "\u8655", "notation_coordinates": null, "notation_content": null}, {"box_type": "Music", "is_excluded_from_dataset": false, "is_line_break": false, "text_coordinates": [[249, 817], [296, 861]], "text_content": "\u541b", "notation_coordinates": null, "notation_content": null}, {"box_type": "Music", "is_excluded_from_dataset": false, "is_line_break": false, "text_coordinates": [[246, 861], [307, 911]], "text_content": "\u8a66", "notation_coordinates": null, "notation_content": null}, {"box_type": "Music", "is_excluded_from_dataset": false, "is_line_break": false, "text_coordinates": [[252, 911], [291, 959]], "text_content": "\u770b", "notation_coordinates": null, "notation_content": null}, {"box_type": "Music", "is_excluded_from_dataset": false, "is_line_break": false, "text_coordinates": [[247, 960], [301, 1014]], "text_content": "\u5960", "notation_coordinates": null, "notation_content": null}, {"box_type": "Music", "is_excluded_from_dataset": false, "is_line_break": false, "text_coordinates": [[250, 1017], [301, 1061]], "text_content": "\u6dee", "notation_coordinates": null, "notation_content": null}, {"box_type": "Music", "is_excluded_from_dataset": false, "is_line_break": true, "text_coordinates": [[251, 1068], [300, 1105]], "text_content": "\u53f3", "notation_coordinates": null, "notation_content": null}, {"box_type": "Music", "is_excluded_from_dataset": false, "is_line_break": false, "text_coordinates": [[153, 53], [205, 87]], "text_content": "\u963b", "notation_coordinates": null, "notation_content": null}, {"box_type": "Music", "is_excluded_from_dataset": false, "is_line_break": false, "text_coordinates": [[149, 105], [207, 142]], "text_content": "\u6c5f", "notation_coordinates": null, "notation_content": null}, {"box_type": "Music", "is_excluded_from_dataset": false, "is_line_break": false, "text_coordinates": [[158, 149], [204, 196]], "text_content": "\u5357", "notation_coordinates": null, "notation_content": null}, {"box_type": "Music", "is_excluded_from_dataset": false, "is_line_break": false, "text_coordinates": [[154, 202], [212, 252]], "text_content": "\u9063", "notation_coordinates": null, "notation_content": null}, {"box_type": "Music", "is_excluded_from_dataset": false, "is_line_break": false, "text_coordinates": [[156, 262], [207, 293]], "text_content": "\u516d", "notation_coordinates": null, "notation_content": null}, {"box_type": "Music", "is_excluded_from_dataset": false, "is_line_break": false, "text_coordinates": [[157, 314], [205, 347]], "text_content": "\u4e01", "notation_coordinates": null, "notation_content": null}, {"box_type": "Music", "is_excluded_from_dataset": false, "is_line_break": false, "text_coordinates": [[159, 359], [205, 405]], "text_content": "\u96f7", "notation_coordinates": null, "notation_content": null}, {"box_type": "Music", "is_excluded_from_dataset": false, "is_line_break": false, "text_coordinates": [[161, 411], [209, 457]], "text_content": "\u96fb", "notation_coordinates": null, "notation_content": null}, {"box_type": "Music", "is_excluded_from_dataset": false, "is_line_break": false, "text_coordinates": [[158, 461], [202, 505]], "text_content": "\u5225", "notation_coordinates": null, "notation_content": null}, {"box_type": "Music", "is_excluded_from_dataset": false, "is_line_break": false, "text_coordinates": [[160, 510], [205, 557]], "text_content": "\u5b88", "notation_coordinates": null, "notation_content": null}, {"box_type": "Music", "is_excluded_from_dataset": false, "is_line_break": false, "text_coordinates": [[157, 560], [212, 608]], "text_content": "\u6771", "notation_coordinates": null, "notation_content": null}, {"box_type": "Music", "is_excluded_from_dataset": false, "is_line_break": false, "text_coordinates": [[162, 610], [205, 658]], "text_content": "\u95dc", "notation_coordinates": null, "notation_content": null}, {"box_type": "Music", "is_excluded_from_dataset": false, "is_line_break": false, "text_coordinates": [[153, 664], [206, 708]], "text_content": "\ud861\udeab", "notation_coordinates": null, "notation_content": null}, {"box_type": "Music", "is_excluded_from_dataset": false, "is_line_break": false, "text_coordinates": [[166, 712], [215, 760]], "text_content": "\u7b11", "notation_coordinates": null, "notation_content": null}, {"box_type": "Music", "is_excluded_from_dataset": false, "is_line_break": false, "text_coordinates": [[157, 760], [215, 809]], "text_content": "\u82f1", "notation_coordinates": null, "notation_content": null}, {"box_type": "Music", "is_excluded_from_dataset": false, "is_line_break": false, "text_coordinates": [[159, 814], [213, 858]], "text_content": "\u96c4", "notation_coordinates": null, "notation_content": null}, {"box_type": "Music", "is_excluded_from_dataset": false, "is_line_break": false, "text_coordinates": [[155, 863], [212, 906]], "text_content": "\u7121", "notation_coordinates": null, "notation_content": null}, {"box_type": "Music", "is_excluded_from_dataset": false, "is_line_break": false, "text_coordinates": [[157, 917], [215, 960]], "text_content": "\u597d", "notation_coordinates": null, "notation_content": null}, {"box_type": "Music", "is_excluded_from_dataset": false, "is_line_break": false, "text_coordinates": [[165, 964], [204, 1010]], "text_content": "\u624b", "notation_coordinates": null, "notation_content": null}, {"box_type": "Music", "is_excluded_from_dataset": false, "is_line_break": false, "text_coordinates": [[162, 1029], [211, 1037]], "text_content": "\u4e00", "notation_coordinates": null, "notation_content": null}, {"box_type": "Music", "is_excluded_from_dataset": false, "is_line_break": true, "text_coordinates": [[170, 1066], [209, 1117]], "text_content": "\u7bd9", "notation_coordinates": null, "notation_content": null}, {"box_type": "Music", "is_excluded_from_dataset": false, "is_line_break": false, "text_coordinates": [[58, 48], [116, 93]], "text_content": "\u6625", "notation_coordinates": null, "notation_content": null}, {"box_type": "Music", "is_excluded_from_dataset": false, "is_line_break": false, "text_coordinates": [[62, 103], [120, 141]], "text_content": "\u6c34", "notation_coordinates": null, "notation_content": null}, {"box_type": "Music", "is_excluded_from_dataset": false, "is_line_break": false, "text_coordinates": [[64, 149], [121, 197]], "text_content": "\u8d70", "notation_coordinates": null, "notation_content": null}, {"box_type": "Music", "is_excluded_from_dataset": false, "is_line_break": false, "text_coordinates": [[70, 198], [106, 250]], "text_content": "\u66f9", "notation_coordinates": null, "notation_content": null}, {"box_type": "Music", "is_excluded_from_dataset": false, "is_line_break": false, "text_coordinates": [[65, 252], [115, 298]], "text_content": "\u779e", "notation_coordinates": null, "notation_content": null}, {"box_type": "Music", "is_excluded_from_dataset": false, "is_line_break": false, "text_coordinates": [[64, 315], [122, 350]], "text_content": "\u53c8", "notation_coordinates": null, "notation_content": null}, {"box_type": "Music", "is_excluded_from_dataset": false, "is_line_break": false, "text_coordinates": [[69, 359], [116, 404]], "text_content": "\u600e", "notation_coordinates": null, "notation_content": null}, {"box_type": "Music", "is_excluded_from_dataset": false, "is_line_break": false, "text_coordinates": [[62, 415], [117, 448]], "text_content": "\u77e5", "notation_coordinates": null, "notation_content": null}, {"box_type": "Music", "is_excluded_from_dataset": false, "is_line_break": false, "text_coordinates": [[65, 462], [126, 496]], "text_content": "\u4eba", "notation_coordinates": null, "notation_content": null}, {"box_type": "Music", "is_excluded_from_dataset": false, "is_line_break": false, "text_coordinates": [[60, 508], [119, 553]], "text_content": "\u5728", "notation_coordinates": null, "notation_content": null}, {"box_type": "Music", "is_excluded_from_dataset": false, "is_line_break": false, "text_coordinates": [[66, 563], [116, 597]], "text_content": "\u5c0f", "notation_coordinates": null, "notation_content": null}, {"box_type": "Music", "is_excluded_from_dataset": false, "is_line_break": false, "text_coordinates": [[62, 617], [119, 654]], "text_content": "\u7d05", "notation_coordinates": null, "notation_content": null}, {"box_type": "Music", "is_excluded_from_dataset": false, "is_line_break": false, "text_coordinates": [[63, 658], [121, 706]], "text_content": "\u6a13", "notation_coordinates": null, "notation_content": null}, {"box_type": "Music", "is_excluded_from_dataset": false, "is_line_break": false, "text_coordinates": [[64, 710], [116, 767]], "text_content": "\u7c3e", "notation_coordinates": null, "notation_content": null}, {"box_type": "Music", "is_excluded_from_dataset": false, "is_line_break": false, "text_coordinates": [[66, 767], [115, 815]], "text_content": "\u5f71", "notation_coordinates": null, "notation_content": null}, {"box_type": "Music", "is_excluded_from_dataset": false, "is_line_break": false, "text_coordinates": [[77, 817], [119, 863]], "text_content": "\u9593", "notation_coordinates": null, "notation_content": null}]}