{"version": "2.0", "notation_type": "None", "composer": "\u59dc\u5914", "mode_properties": {"gong_lvlv": "None", "final_note": "None"}, "content": [{"box_type": "Title", "text_content": "\u4f10\u529f\u7e7c"}, {"box_type": "Mode", "text_content": ""}, {"box_type": "Preface", "text_content": "\u4f10\u529f\u7e7c\uff0c\u514b\u6cb3\u6771\u4e5f\u3002\u59cb\u592a\u7956\u4e4b\u4f10\u6cb3\u6771\uff0c\u8a93\u4e0d\u6bba\u4e00\u4eba\u3002\n\u53c8\u54c0\u5289\u6c0f\u4e4b\u4e0d\u7940\uff0c\u6545\u7de9\u53d6\u4e4b\uff0c\u81f3\u592a\u5b97\u59cb\u5f97\u5176\u5730\u3002\n"}, {"box_type": "Unmarked", "text_content": ""}, {"box_type": "Music", "text_content": "\u4f10", "notation_content": null, "is_line_break": false}, {"box_type": "Music", "text_content": "\u529f", "notation_content": null, "is_line_break": false}, {"box_type": "Music", "text_content": "\u7e7c\uff0c", "notation_content": null, "is_line_break": false}, {"box_type": "Music", "text_content": "\u5401", "notation_content": null, "is_line_break": false}, {"box_type": "Music", "text_content": "\u4ee5", "notation_content": null, "is_line_break": false}, {"box_type": "Music", "text_content": "\u6642\u3002", "notation_content": null, "is_line_break": false}, {"box_type": "Music", "text_content": "\u70c8", "notation_content": null, "is_line_break": false}, {"box_type": "Music", "text_content": "\u7956", "notation_content": null, "is_line_break": false}, {"box_type": "Music", "text_content": "\u6709", "notation_content": null, "is_line_break": false}, {"box_type": "Music", "text_content": "\u9020\uff0c", "notation_content": null, "is_line_break": false}, {"box_type": "Music", "text_content": "\u592a", "notation_content": null, "is_line_break": false}, {"box_type": "Music", "text_content": "\u5b97", "notation_content": null, "is_line_break": false}, {"box_type": "Music", "text_content": "\u6fdf", "notation_content": null, "is_line_break": false}, {"box_type": "Music", "text_content": "\u4e4b\u3002", "notation_content": null, "is_line_break": false}, {"box_type": "Music", "text_content": "\u6cb3", "notation_content": null, "is_line_break": false}, {"box_type": "Music", "text_content": "\u6771", "notation_content": null, "is_line_break": false}, {"box_type": "Music", "text_content": "\u96d6", "notation_content": null, "is_line_break": false}, {"box_type": "Music", "text_content": "\u5fae\uff0c", "notation_content": null, "is_line_break": false}, {"box_type": "Music", "text_content": "\u65b9", "notation_content": null, "is_line_break": false}, {"box_type": "Music", "text_content": "\u547d", "notation_content": null, "is_line_break": false}, {"box_type": "Music", "text_content": "\u518d", "notation_content": null, "is_line_break": false}, {"box_type": "Music", "text_content": "\u4e16\u3002", "notation_content": null, "is_line_break": true}, {"box_type": "Music", "text_content": "\u6cb3", "notation_content": null, "is_line_break": false}, {"box_type": "Music", "text_content": "\u6771", "notation_content": null, "is_line_break": false}, {"box_type": "Music", "text_content": "\u96d6", "notation_content": null, "is_line_break": false}, {"box_type": "Music", "text_content": "\u5f3a\uff0c", "notation_content": null, "is_line_break": false}, {"box_type": "Music", "text_content": "\u5352", "notation_content": null, "is_line_break": false}, {"box_type": "Music", "text_content": "\u596a", "notation_content": null, "is_line_break": false}, {"box_type": "Music", "text_content": "\u5176", "notation_content": null, "is_line_break": false}, {"box_type": "Music", "text_content": "\u5e25\u3002", "notation_content": null, "is_line_break": false}, {"box_type": "Music", "text_content": "\u60df", "notation_content": null, "is_line_break": false}, {"box_type": "Music", "text_content": "\u6f22", "notation_content": null, "is_line_break": false}, {"box_type": "Music", "text_content": "\u4e4b", "notation_content": null, "is_line_break": false}, {"box_type": "Music", "text_content": "\u8449\uff0c", "notation_content": null, "is_line_break": false}, {"box_type": "Music", "text_content": "\u4fdd", "notation_content": null, "is_line_break": false}, {"box_type": "Music", "text_content": "\u4e8e", "notation_content": null, "is_line_break": false}, {"box_type": "Music", "text_content": "\u6b64", "notation_content": null, "is_line_break": false}, {"box_type": "Music", "text_content": "\u90fd\u3002", "notation_content": null, "is_line_break": false}, {"box_type": "Music", "text_content": "\u70c8", "notation_content": null, "is_line_break": false}, {"box_type": "Music", "text_content": "\u7956", "notation_content": null, "is_line_break": false}, {"box_type": "Music", "text_content": "\u5ff5", "notation_content": null, "is_line_break": false}, {"box_type": "Music", "text_content": "\u6c5d\uff0c", "notation_content": null, "is_line_break": false}, {"box_type": "Music", "text_content": "\u4e43", "notation_content": null, "is_line_break": false}, {"box_type": "Music", "text_content": "\u8cb8", "notation_content": null, "is_line_break": false}, {"box_type": "Music", "text_content": "\u672a", "notation_content": null, "is_line_break": false}, {"box_type": "Music", "text_content": "\u924f\u3002", "notation_content": null, "is_line_break": true}, {"box_type": "Music", "text_content": "\u4e00", "notation_content": null, "is_line_break": false}, {"box_type": "Music", "text_content": "\u592b", "notation_content": null, "is_line_break": false}, {"box_type": "Music", "text_content": "\u6b98", "notation_content": null, "is_line_break": false}, {"box_type": "Music", "text_content": "\u751f\uff0c", "notation_content": null, "is_line_break": false}, {"box_type": "Music", "text_content": "\u5e1d", "notation_content": null, "is_line_break": false}, {"box_type": "Music", "text_content": "\u4e5f", "notation_content": null, "is_line_break": false}, {"box_type": "Music", "text_content": "\u4e0d", "notation_content": null, "is_line_break": false}, {"box_type": "Music", "text_content": "\u53d6\u3002", "notation_content": null, "is_line_break": false}, {"box_type": "Music", "text_content": "\u96e8", "notation_content": null, "is_line_break": false}, {"box_type": "Music", "text_content": "\u9732", "notation_content": null, "is_line_break": false}, {"box_type": "Music", "text_content": "\u65e2", "notation_content": null, "is_line_break": false}, {"box_type": "Music", "text_content": "\u6d3d\uff0c", "notation_content": null, "is_line_break": false}, {"box_type": "Music", "text_content": "\u6cb3", "notation_content": null, "is_line_break": false}, {"box_type": "Music", "text_content": "\u6771", "notation_content": null, "is_line_break": false}, {"box_type": "Music", "text_content": "\u81ea", "notation_content": null, "is_line_break": false}, {"box_type": "Music", "text_content": "\u8209\u3002", "notation_content": null, "is_line_break": false}, {"box_type": "Music", "text_content": "\u6cb3", "notation_content": null, "is_line_break": false}, {"box_type": "Music", "text_content": "\u6771", "notation_content": null, "is_line_break": false}, {"box_type": "Music", "text_content": "\u65e2", "notation_content": null, "is_line_break": false}, {"box_type": "Music", "text_content": "\u5e73\uff0c", "notation_content": null, "is_line_break": false}, {"box_type": "Music", "text_content": "\u4e5d", "notation_content": null, "is_line_break": false}, {"box_type": "Music", "text_content": "\u6709", "notation_content": null, "is_line_break": false}, {"box_type": "Music", "text_content": "\u4ee5", "notation_content": null, "is_line_break": false}, {"box_type": "Music", "text_content": "\u5be7\u3002", "notation_content": null, "is_line_break": true}, {"box_type": "Music", "text_content": "\u55da", "notation_content": null, "is_line_break": false}, {"box_type": "Music", "text_content": "\u547c", "notation_content": null, "is_line_break": false}, {"box_type": "Music", "text_content": "\u592a", "notation_content": null, "is_line_break": false}, {"box_type": "Music", "text_content": "\u5b97\uff0c", "notation_content": null, "is_line_break": false}, {"box_type": "Music", "text_content": "\u7e7c", "notation_content": null, "is_line_break": false}, {"box_type": "Music", "text_content": "\u4f10", "notation_content": null, "is_line_break": false}, {"box_type": "Music", "text_content": "\u6709", "notation_content": null, "is_line_break": false}, {"box_type": "Music", "text_content": "\u8072\u3002", "notation_content": null, "is_line_break": false}]}