{"version": "2.0", "notation_type": "Text", "composer": "\u59dc\u5914", "mode_properties": {"gong_lvlv": "None", "final_note": "None"}, "images": ["../../images/zhu_edition_041.png"], "content": [{"box_type": "Title", "is_excluded_from_dataset": false, "is_line_break": false, "text_coordinates": [[441, 120], [497, 166]], "text_content": "\u5c11"}, {"box_type": "Title", "is_excluded_from_dataset": false, "is_line_break": false, "text_coordinates": [[443, 170], [500, 214]], "text_content": "\u5e74"}, {"box_type": "Title", "is_excluded_from_dataset": false, "is_line_break": true, "text_coordinates": [[441, 218], [500, 264]], "text_content": "\u904a"}, {"box_type": "Preface", "is_excluded_from_dataset": false, "is_line_break": false, "text_coordinates": [[373, 168], [434, 215]], "text_content": "\u6232"}, {"box_type": "Preface", "is_excluded_from_dataset": false, "is_line_break": false, "text_coordinates": [[374, 220], [435, 264]], "text_content": "\u5e73"}, {"box_type": "Preface", "is_excluded_from_dataset": false, "is_line_break": true, "text_coordinates": [[373, 264], [434, 312]], "text_content": "\u752b"}, {"box_type": "Music", "is_excluded_from_dataset": false, "is_line_break": false, "text_coordinates": [[308, 21], [368, 68]], "text_content": "\u96d9", "notation_coordinates": null, "notation_content": null}, {"box_type": "Music", "is_excluded_from_dataset": false, "is_line_break": false, "text_coordinates": [[307, 72], [364, 118]], "text_content": "\u87ba", "notation_coordinates": null, "notation_content": null}, {"box_type": "Music", "is_excluded_from_dataset": false, "is_line_break": false, "text_coordinates": [[306, 120], [369, 165]], "text_content": "\u672a", "notation_coordinates": null, "notation_content": null}, {"box_type": "Music", "is_excluded_from_dataset": false, "is_line_break": false, "text_coordinates": [[307, 168], [368, 214]], "text_content": "\u5408", "notation_coordinates": null, "notation_content": null}, {"box_type": "Music", "is_excluded_from_dataset": false, "is_line_break": false, "text_coordinates": [[305, 217], [368, 262]], "text_content": "\u96d9", "notation_coordinates": null, "notation_content": null}, {"box_type": "Music", "is_excluded_from_dataset": false, "is_line_break": false, "text_coordinates": [[308, 262], [367, 313]], "text_content": "\u86fe", "notation_coordinates": null, "notation_content": null}, {"box_type": "Music", "is_excluded_from_dataset": false, "is_line_break": false, "text_coordinates": [[306, 314], [366, 360]], "text_content": "\u5148", "notation_coordinates": null, "notation_content": null}, {"box_type": "Music", "is_excluded_from_dataset": false, "is_line_break": false, "text_coordinates": [[304, 362], [367, 409]], "text_content": "\u6582", "notation_coordinates": null, "notation_content": null}, {"box_type": "Music", "is_excluded_from_dataset": false, "is_line_break": false, "text_coordinates": [[305, 411], [365, 457]], "text_content": "\u5bb6", "notation_coordinates": null, "notation_content": null}, {"box_type": "Music", "is_excluded_from_dataset": false, "is_line_break": false, "text_coordinates": [[306, 460], [365, 506]], "text_content": "\u5728", "notation_coordinates": null, "notation_content": null}, {"box_type": "Music", "is_excluded_from_dataset": false, "is_line_break": false, "text_coordinates": [[305, 507], [366, 555]], "text_content": "\u78a7", "notation_coordinates": null, "notation_content": null}, {"box_type": "Music", "is_excluded_from_dataset": false, "is_line_break": false, "text_coordinates": [[304, 557], [364, 601]], "text_content": "\u96f2", "notation_coordinates": null, "notation_content": null}, {"box_type": "Music", "is_excluded_from_dataset": false, "is_line_break": false, "text_coordinates": [[304, 606], [368, 647]], "text_content": "\u897f", "notation_coordinates": null, "notation_content": null}, {"box_type": "Music", "is_excluded_from_dataset": false, "is_line_break": false, "text_coordinates": [[303, 652], [361, 697]], "text_content": "\u5225", "notation_coordinates": null, "notation_content": null}, {"box_type": "Music", "is_excluded_from_dataset": false, "is_line_break": false, "text_coordinates": [[304, 702], [366, 744]], "text_content": "\u6bcd", "notation_coordinates": null, "notation_content": null}, {"box_type": "Music", "is_excluded_from_dataset": false, "is_line_break": false, "text_coordinates": [[306, 746], [365, 796]], "text_content": "\u60c5", "notation_coordinates": null, "notation_content": null}, {"box_type": "Music", "is_excluded_from_dataset": false, "is_line_break": false, "text_coordinates": [[305, 797], [365, 842]], "text_content": "\u61f7", "notation_coordinates": null, "notation_content": null}, {"box_type": "Music", "is_excluded_from_dataset": false, "is_line_break": false, "text_coordinates": [[307, 845], [366, 889]], "text_content": "\u96a8", "notation_coordinates": null, "notation_content": null}, {"box_type": "Music", "is_excluded_from_dataset": false, "is_line_break": false, "text_coordinates": [[304, 894], [362, 936]], "text_content": "\u90ce", "notation_coordinates": null, "notation_content": null}, {"box_type": "Music", "is_excluded_from_dataset": false, "is_line_break": false, "text_coordinates": [[307, 938], [363, 983]], "text_content": "\u6ecb", "notation_coordinates": null, "notation_content": null}, {"box_type": "Music", "is_excluded_from_dataset": false, "is_line_break": true, "text_coordinates": [[307, 985], [364, 1034]], "text_content": "\u5473", "notation_coordinates": null, "notation_content": null}, {"box_type": "Music", "is_excluded_from_dataset": false, "is_line_break": false, "text_coordinates": [[239, 21], [301, 66]], "text_content": "\u6843", "notation_coordinates": null, "notation_content": null}, {"box_type": "Music", "is_excluded_from_dataset": false, "is_line_break": false, "text_coordinates": [[240, 70], [301, 116]], "text_content": "\u8449", "notation_coordinates": null, "notation_content": null}, {"box_type": "Music", "is_excluded_from_dataset": false, "is_line_break": false, "text_coordinates": [[244, 119], [300, 164]], "text_content": "\u6e21", "notation_coordinates": null, "notation_content": null}, {"box_type": "Music", "is_excluded_from_dataset": false, "is_line_break": false, "text_coordinates": [[243, 171], [299, 212]], "text_content": "\u6c5f", "notation_coordinates": null, "notation_content": null}, {"box_type": "Music", "is_excluded_from_dataset": false, "is_line_break": false, "text_coordinates": [[243, 217], [301, 264]], "text_content": "\u6642", "notation_coordinates": null, "notation_content": null}, {"box_type": "Music", "is_excluded_from_dataset": false, "is_line_break": false, "text_coordinates": [[245, 267], [296, 308]], "text_content": " ", "notation_coordinates": null, "notation_content": null}, {"box_type": "Music", "is_excluded_from_dataset": false, "is_line_break": false, "text_coordinates": [[239, 313], [296, 359]], "text_content": "\u6241", "notation_coordinates": null, "notation_content": null}, {"box_type": "Music", "is_excluded_from_dataset": false, "is_line_break": false, "text_coordinates": [[239, 363], [298, 408]], "text_content": "\u821f", "notation_coordinates": null, "notation_content": null}, {"box_type": "Music", "is_excluded_from_dataset": false, "is_line_break": false, "text_coordinates": [[239, 410], [299, 457]], "text_content": "\u8f09", "notation_coordinates": null, "notation_content": null}, {"box_type": "Music", "is_excluded_from_dataset": false, "is_line_break": false, "text_coordinates": [[244, 460], [292, 504]], "text_content": "\u4e86", "notation_coordinates": null, "notation_content": null}, {"box_type": "Music", "is_excluded_from_dataset": false, "is_line_break": false, "text_coordinates": [[240, 507], [298, 553]], "text_content": "\u60a4", "notation_coordinates": null, "notation_content": null}, {"box_type": "Music", "is_excluded_from_dataset": false, "is_line_break": false, "text_coordinates": [[239, 556], [297, 599]], "text_content": "\u60a4", "notation_coordinates": null, "notation_content": null}, {"box_type": "Music", "is_excluded_from_dataset": false, "is_line_break": false, "text_coordinates": [[239, 603], [300, 650]], "text_content": "\u6b78", "notation_coordinates": null, "notation_content": null}, {"box_type": "Music", "is_excluded_from_dataset": false, "is_line_break": false, "text_coordinates": [[238, 650], [297, 695]], "text_content": "\u53bb", "notation_coordinates": null, "notation_content": null}, {"box_type": "Music", "is_excluded_from_dataset": false, "is_line_break": false, "text_coordinates": [[237, 698], [297, 743]], "text_content": "\u4eca", "notation_coordinates": null, "notation_content": null}, {"box_type": "Music", "is_excluded_from_dataset": false, "is_line_break": false, "text_coordinates": [[236, 748], [296, 795]], "text_content": "\u591c", "notation_coordinates": null, "notation_content": null}, {"box_type": "Music", "is_excluded_from_dataset": false, "is_line_break": false, "text_coordinates": [[242, 799], [292, 840]], "text_content": "\u6cca", "notation_coordinates": null, "notation_content": null}, {"box_type": "Music", "is_excluded_from_dataset": false, "is_line_break": false, "text_coordinates": [[237, 843], [297, 889]], "text_content": "\u524d", "notation_coordinates": null, "notation_content": null}, {"box_type": "Music", "is_excluded_from_dataset": false, "is_line_break": false, "text_coordinates": [[241, 893], [293, 937]], "text_content": "\u6eaa", "notation_coordinates": null, "notation_content": null}, {"box_type": "Music", "is_excluded_from_dataset": false, "is_line_break": false, "text_coordinates": [[237, 941], [298, 984]], "text_content": "\u694a", "notation_coordinates": null, "notation_content": null}, {"box_type": "Music", "is_excluded_from_dataset": false, "is_line_break": true, "text_coordinates": [[237, 988], [293, 1034]], "text_content": "\u67f3", "notation_coordinates": null, "notation_content": null}, {"box_type": "Music", "is_excluded_from_dataset": false, "is_line_break": false, "text_coordinates": [[182, 20], [235, 66]], "text_content": "\u6d25", "notation_coordinates": null, "notation_content": null}, {"box_type": "Music", "is_excluded_from_dataset": false, "is_line_break": false, "text_coordinates": [[175, 72], [235, 116]], "text_content": "\u982d", "notation_coordinates": null, "notation_content": null}, {"box_type": "Music", "is_excluded_from_dataset": false, "is_line_break": false, "text_coordinates": [[176, 121], [232, 164]], "text_content": "\u68c3", "notation_coordinates": null, "notation_content": null}, {"box_type": "Music", "is_excluded_from_dataset": false, "is_line_break": false, "text_coordinates": [[176, 169], [232, 213]], "text_content": "\u82b1", "notation_coordinates": null, "notation_content": null}, {"box_type": "Music", "is_excluded_from_dataset": false, "is_line_break": false, "text_coordinates": [[176, 215], [232, 262]], "text_content": "\u7246", "notation_coordinates": null, "notation_content": null}, {"box_type": "Music", "is_excluded_from_dataset": false, "is_line_break": false, "text_coordinates": [[177, 264], [232, 309]], "text_content": "\u5916", "notation_coordinates": null, "notation_content": null}, {"box_type": "Music", "is_excluded_from_dataset": false, "is_line_break": false, "text_coordinates": [[175, 316], [232, 355]], "text_content": "\u5fc3", "notation_coordinates": null, "notation_content": null}, {"box_type": "Music", "is_excluded_from_dataset": false, "is_line_break": false, "text_coordinates": [[175, 359], [234, 410]], "text_content": "\u4e8b", "notation_coordinates": null, "notation_content": null}, {"box_type": "Music", "is_excluded_from_dataset": false, "is_line_break": false, "text_coordinates": [[174, 411], [232, 453]], "text_content": "\u5169", "notation_coordinates": null, "notation_content": null}, {"box_type": "Music", "is_excluded_from_dataset": false, "is_line_break": false, "text_coordinates": [[172, 459], [232, 502]], "text_content": "\u4eba", "notation_coordinates": null, "notation_content": null}, {"box_type": "Music", "is_excluded_from_dataset": false, "is_line_break": false, "text_coordinates": [[172, 510], [229, 548]], "text_content": "\u77e5", "notation_coordinates": null, "notation_content": null}]}