{"version": "2.0", "notation_type": "Text", "composer": "\u59dc\u5914", "mode_properties": {"gong_lvlv": "None", "final_note": "None"}, "content": [{"box_type": "Title", "text_content": "\u63a2\u6625\u6162"}, {"box_type": "Mode", "text_content": ""}, {"box_type": "Preface", "text_content": "\u4e88\u81ea\u5b69\u5e7c\u5f9e\u5148\u4eba\u5ba6\u65bc\u53e4\u6c94\uff0c\u5973\u9808\u56e0\u5ac1\u7109\u3002\n\u4e2d\u53bb\u5fa9\u4f86\u5e7e\u4e8c\u5341\u5e74\uff0c\u8c48\u60df\u59ca\u5f1f\u4e4b\u611b\uff0c\n\u6c94\u4e4b\u7236\u8001\u5152\u5973\u5b50\u4ea6\u83ab\u4e0d\u4e88\u611b\u4e5f\u3002\u4e19\u5348\u51ac\uff0c\n\u5343\u5dd6\u8001\u4eba\u7d04\u4e88\u904e\u82d5\u9705\uff0c\u6b72\u665a\u4e58\u6fe4\u8f09\u96ea\u800c\u4e0b\uff0c\n\u9867\u5ff5\u4f9d\u4f9d\uff0c\u6b86\u4e0d\u80fd\u53bb\u3002\u4f5c\u6b64\u66f2\u5225\u912d\u6b21\u81ef\u3001\n\u8f9b\u514b\u6e05\u3001\u59da\u525b\u4e2d\u8af8\u541b\u3002\n"}, {"box_type": "Unmarked", "text_content": ""}, {"box_type": "Music", "text_content": "\u8870", "notation_content": null, "is_line_break": false}, {"box_type": "Music", "text_content": "\u8349", "notation_content": null, "is_line_break": false}, {"box_type": "Music", "text_content": "\u6101", "notation_content": null, "is_line_break": false}, {"box_type": "Music", "text_content": "\u7159\uff0c", "notation_content": null, "is_line_break": false}, {"box_type": "Music", "text_content": "\u4e82", "notation_content": null, "is_line_break": false}, {"box_type": "Music", "text_content": "\u9d09", "notation_content": null, "is_line_break": false}, {"box_type": "Music", "text_content": "\u9001", "notation_content": null, "is_line_break": false}, {"box_type": "Music", "text_content": "\u65e5\uff0c", "notation_content": null, "is_line_break": false}, {"box_type": "Music", "text_content": "\u98a8", "notation_content": null, "is_line_break": false}, {"box_type": "Music", "text_content": "\u6c99", "notation_content": null, "is_line_break": false}, {"box_type": "Music", "text_content": "\u56de", "notation_content": null, "is_line_break": false}, {"box_type": "Music", "text_content": "\u65cb", "notation_content": null, "is_line_break": false}, {"box_type": "Music", "text_content": "\u5e73", "notation_content": null, "is_line_break": false}, {"box_type": "Music", "text_content": "\u91ce\u3002", "notation_content": null, "is_line_break": false}, {"box_type": "Music", "text_content": "\u62c2", "notation_content": null, "is_line_break": false}, {"box_type": "Music", "text_content": "\u96ea", "notation_content": null, "is_line_break": false}, {"box_type": "Music", "text_content": "\u91d1", "notation_content": null, "is_line_break": false}, {"box_type": "Music", "text_content": "\u97ad\uff0c", "notation_content": null, "is_line_break": false}, {"box_type": "Music", "text_content": "\u6b3a", "notation_content": null, "is_line_break": false}, {"box_type": "Music", "text_content": "\u5bd2", "notation_content": null, "is_line_break": false}, {"box_type": "Music", "text_content": "\u8338", "notation_content": null, "is_line_break": false}, {"box_type": "Music", "text_content": "\u5e3d\uff0c", "notation_content": null, "is_line_break": false}, {"box_type": "Music", "text_content": "\u9084", "notation_content": null, "is_line_break": false}, {"box_type": "Music", "text_content": "\u8a18", "notation_content": null, "is_line_break": false}, {"box_type": "Music", "text_content": "\u7ae0", "notation_content": null, "is_line_break": false}, {"box_type": "Music", "text_content": "\u81fa", "notation_content": null, "is_line_break": false}, {"box_type": "Music", "text_content": "\u8d70", "notation_content": null, "is_line_break": false}, {"box_type": "Music", "text_content": "\u99ac\u3002", "notation_content": null, "is_line_break": false}, {"box_type": "Music", "text_content": "\u8ab0", "notation_content": null, "is_line_break": false}, {"box_type": "Music", "text_content": "\u5ff5", "notation_content": null, "is_line_break": false}, {"box_type": "Music", "text_content": "\u6f02", "notation_content": null, "is_line_break": false}, {"box_type": "Music", "text_content": "\u96f6", "notation_content": null, "is_line_break": false}, {"box_type": "Music", "text_content": "\u4e45\uff0c", "notation_content": null, "is_line_break": false}, {"box_type": "Music", "text_content": "\u8b3e", "notation_content": null, "is_line_break": false}, {"box_type": "Music", "text_content": "\u8d0f", "notation_content": null, "is_line_break": false}, {"box_type": "Music", "text_content": "\u5f97", "notation_content": null, "is_line_break": false}, {"box_type": "Music", "text_content": "\u5e7d", "notation_content": null, "is_line_break": false}, {"box_type": "Music", "text_content": "\u61f7", "notation_content": null, "is_line_break": false}, {"box_type": "Music", "text_content": "\u96e3", "notation_content": null, "is_line_break": false}, {"box_type": "Music", "text_content": "\u5beb\u3002", "notation_content": null, "is_line_break": false}, {"box_type": "Music", "text_content": "\u6545", "notation_content": null, "is_line_break": false}, {"box_type": "Music", "text_content": "\u4eba", "notation_content": null, "is_line_break": false}, {"box_type": "Music", "text_content": "\u6e05", "notation_content": null, "is_line_break": false}, {"box_type": "Music", "text_content": "\u6c94", "notation_content": null, "is_line_break": false}, {"box_type": "Music", "text_content": "\u76f8", "notation_content": null, "is_line_break": false}, {"box_type": "Music", "text_content": "\u9022\uff0c", "notation_content": null, "is_line_break": false}, {"box_type": "Music", "text_content": "\u5c0f", "notation_content": null, "is_line_break": false}, {"box_type": "Music", "text_content": "\u7a97", "notation_content": null, "is_line_break": false}, {"box_type": "Music", "text_content": "\u9591", "notation_content": null, "is_line_break": false}, {"box_type": "Music", "text_content": "\u5171", "notation_content": null, "is_line_break": false}, {"box_type": "Music", "text_content": "\u60c5", "notation_content": null, "is_line_break": false}, {"box_type": "Music", "text_content": "\u8a71\u3002", "notation_content": null, "is_line_break": true}, {"box_type": "Music", "text_content": "\u9577", "notation_content": null, "is_line_break": false}, {"box_type": "Music", "text_content": "\u6068", "notation_content": null, "is_line_break": false}, {"box_type": "Music", "text_content": "\u96e2", "notation_content": null, "is_line_break": false}, {"box_type": "Music", "text_content": "\u591a", "notation_content": null, "is_line_break": false}, {"box_type": "Music", "text_content": "\u6703", "notation_content": null, "is_line_break": false}, {"box_type": "Music", "text_content": "\u5c11\uff0c", "notation_content": null, "is_line_break": false}, {"box_type": "Music", "text_content": "\u91cd", "notation_content": null, "is_line_break": false}, {"box_type": "Music", "text_content": "\u8a2a", "notation_content": null, "is_line_break": false}, {"box_type": "Music", "text_content": "\u554f", "notation_content": null, "is_line_break": false}, {"box_type": "Music", "text_content": "\u7af9", "notation_content": null, "is_line_break": false}, {"box_type": "Music", "text_content": "\u897f\uff0c", "notation_content": null, "is_line_break": false}, {"box_type": "Music", "text_content": "\u73e0", "notation_content": null, "is_line_break": false}, {"box_type": "Music", "text_content": "\u6dda", "notation_content": null, "is_line_break": false}, {"box_type": "Music", "text_content": "\u76c8", "notation_content": null, "is_line_break": false}, {"box_type": "Music", "text_content": "\u628a\u3002", "notation_content": null, "is_line_break": false}, {"box_type": "Music", "text_content": "\u96c1", "notation_content": null, "is_line_break": false}, {"box_type": "Music", "text_content": "\u78e7", "notation_content": null, "is_line_break": false}, {"box_type": "Music", "text_content": "\u6ce2", "notation_content": null, "is_line_break": false}, {"box_type": "Music", "text_content": "\u5e73\uff0c", "notation_content": null, "is_line_break": false}, {"box_type": "Music", "text_content": "\u6f01", "notation_content": null, "is_line_break": false}, {"box_type": "Music", "text_content": "\u6c40", "notation_content": null, "is_line_break": false}, {"box_type": "Music", "text_content": "\u4eba", "notation_content": null, "is_line_break": false}, {"box_type": "Music", "text_content": "\u6563\uff0c", "notation_content": null, "is_line_break": false}, {"box_type": "Music", "text_content": "\u8001", "notation_content": null, "is_line_break": false}, {"box_type": "Music", "text_content": "\u53bb", "notation_content": null, "is_line_break": false}, {"box_type": "Music", "text_content": "\u4e0d", "notation_content": null, "is_line_break": false}, {"box_type": "Music", "text_content": "\u582a", "notation_content": null, "is_line_break": false}, {"box_type": "Music", "text_content": "\u904a", "notation_content": null, "is_line_break": false}, {"box_type": "Music", "text_content": "\u51b6\u3002", "notation_content": null, "is_line_break": false}, {"box_type": "Music", "text_content": "\u7121", "notation_content": null, "is_line_break": false}, {"box_type": "Music", "text_content": "\u67f0", "notation_content": null, "is_line_break": false}, {"box_type": "Music", "text_content": "\u82d5", "notation_content": null, "is_line_break": false}, {"box_type": "Music", "text_content": "\u6eaa", "notation_content": null, "is_line_break": false}, {"box_type": "Music", "text_content": "\u6708\uff0c", "notation_content": null, "is_line_break": false}, {"box_type": "Music", "text_content": "\u53c8", "notation_content": null, "is_line_break": false}, {"box_type": "Music", "text_content": "\u559a", "notation_content": null, "is_line_break": false}, {"box_type": "Music", "text_content": "\u6211", "notation_content": null, "is_line_break": false}, {"box_type": "Music", "text_content": "\u6241", "notation_content": null, "is_line_break": false}, {"box_type": "Music", "text_content": "\u821f", "notation_content": null, "is_line_break": false}, {"box_type": "Music", "text_content": "\u6771", "notation_content": null, "is_line_break": false}, {"box_type": "Music", "text_content": "\u4e0b\u3002", "notation_content": null, "is_line_break": false}, {"box_type": "Music", "text_content": "\u751a", "notation_content": null, "is_line_break": false}, {"box_type": "Music", "text_content": "\u65e5", "notation_content": null, "is_line_break": false}, {"box_type": "Music", "text_content": "\u6b78", "notation_content": null, "is_line_break": false}, {"box_type": "Music", "text_content": "\u4f86\uff0c", "notation_content": null, "is_line_break": false}, {"box_type": "Music", "text_content": "\u6885", "notation_content": null, "is_line_break": false}, {"box_type": "Music", "text_content": "\u82b1", "notation_content": null, "is_line_break": false}, {"box_type": "Music", "text_content": "\u96f6", "notation_content": null, "is_line_break": false}, {"box_type": "Music", "text_content": "\u843d", "notation_content": null, "is_line_break": false}, {"box_type": "Music", "text_content": "\u6625", "notation_content": null, "is_line_break": false}, {"box_type": "Music", "text_content": "\u591c\u3002", "notation_content": null, "is_line_break": false}]}